Workbook

Sheet Sales_data
A1: Order_ID | B1: Customer_ID | C1: Product_ID | D1: Order_Date | E1: Delivery_Date | F1: Customer_Name | G1: Gender | H1: DOB | I1: City | J1: Region | K1: Category | L1: Product_Name | M1: Quantity | N1: Unit_Price | O1: Discount_% | P1: Sales | Q1: Rating | R1: Payment_Mode | S1: Salesperson | T1: Email | U1: Phone | V1: Order_Status | W1: Customer Classification
A2: ORD10001 | B2: C008 | C2: P202 | D2: 18/09/2025 | E2: 22/09/2025 | F2: Kavya Nair | G2: Female | H2: 01/08/1976 | I2: Hyderabad | J2: South | K2: Home Appliances | L2: Iron | M2: 4 | N2: 2200 | O2: 10 | P2: 7920 | Q2: 4 | R2: Cash | S2: Ritika | T2: KAvya.nair@company.com | U2: 9431429797 | V2: Completed | W2: =IF(OR(Q2<=2,V2="Cancelled"),"Blacklisted",IF(AND(P2>=100000,Q2>=4,O2<=10%,V2="Completed"),"Platinum",IF(AND(P2>=50000,P2<100000,Q2>=3,V2="Completed"),"Gold",IF(AND(P2<50000,V2="Completed"),"Silver","Blacklisted")))) -> Silver
A3: ORD10002 | B3: C008 | C3: P104 | D3: 27/04/2025 | E3: 04/05/2025 | F3: Kavya Nair | G3: Female | H3: 16/10/2000 | I3: Delhi | J3: North | K3: Electronics | L3: Monitor | M3: 17 | N3: 12000 | O3: 10 | P3: 183600 | Q3: 1 | R3: NetBanking | S3: Rahul | T3: kavya.nair@company.com | U3: 9129865339 | V3: Completed | W3: =IF(OR(Q3<=2,V3="Cancelled"),"Blacklisted",IF(AND(P3>=100000,Q3>=4,O3<=10%,V3="Completed"),"Platinum",IF(AND(P3>=50000,P3<100000,Q3>=3,V3="Completed"),"Gold",IF(AND(P3<50000,V3="Completed"),"Silver","Blacklisted")))) -> Blacklisted
A4: ORD10003 | B4: C010 | C4: P101 | D4: 03/09/2025 | E4: 14/09/2025 | F4: pooja shah | G4: Female | H4: 16/09/1994 | I4: Bengaluru | J4: South | K4: Electronics | L4: Laptop | M4: 5 | N4: 55000 | O4: 5 | P4: 261250 | Q4: 3 | R4: NetBanking | S4: Aisha | T4: pooja.shah@company.com | U4: 9380975626 | V4: Pending | W4: =IF(OR(Q4<=2,V4="Cancelled"),"Blacklisted",IF(AND(P4>=100000,Q4>=4,O4<=10%,V4="Completed"),"Platinum",IF(AND(P4>=50000,P4<100000,Q4>=3,V4="Completed"),"Gold",IF(AND(P4<50000,V4="Completed"),"Silver","Blacklisted")))) -> Blacklisted
A5: ORD10002 | B5: C008 | C5: P202 | D5: 21/03/2026 | E5: 02/04/2026 | F5: Kavya Nair | G5: Female | H5: 07/03/2004 | I5: Bengaluru | J5: South | K5: Home Appliances | L5: Iron | M5: 5 | N5: 2200 | O5: 5 | P5: 10450 | Q5: 5 | R5: NetBanking | S5: Aisha | T5: kavya.nair@company.com | U5: 9600261125 | V5: Cancelled | W5: =IF(OR(Q5<=2,V5="Cancelled"),"Blacklisted",IF(AND(P5>=100000,Q5>=4,O5<=10%,V5="Completed"),"Platinum",IF(AND(P5>=50000,P5<100000,Q5>=3,V5="Completed"),"Gold",IF(AND(P5<50000,V5="Completed"),"Silver","Blacklisted")))) -> Blacklisted
A6: ORD10005 | B6: C009 | C6: P103 | D6: 27/09/2025 | E6: 07/10/2025 | F6: Mohit Verma | G6: Male | H6: 13/04/1976 | I6: Delhi | J6: North | K6: Electronics | L6: Keyboard | M6: 8 | N6: 1200 | O6: 5 | P6: 9120 | Q6: 2 | R6: Card | S6: Aisha | T6: mohit.verma@company.com | U6: 9724635978 | V6: Pending | W6: =IF(OR(Q6<=2,V6="Cancelled"),"Blacklisted",IF(AND(P6>=100000,Q6>=4,O6<=10%,V6="Completed"),"Platinum",IF(AND(P6>=50000,P6<100000,Q6>=3,V6="Completed"),"Gold",IF(AND(P6<50000,V6="Completed"),"Silver","Blacklisted")))) -> Blacklisted
A7: ORD10006 | B7: C007 | C7: P202 | D7: 04/01/2026 | E7: 12/01/2026 | F7: arjun Rao | G7: Male | H7: 07/02/1988 | I7: Hyderabad | J7: South | K7: Home Appliances | L7: Iron | M7: 4 | N7: 2200 | O7: 0 | P7: 8800 | Q7: 1 | R7: UPI | S7: Ritika | T7: arjun.rao@company.com | U7: 9780584905 | V7: Completed | W7: =IF(OR(Q7<=2,V7="Cancelled"),"Blacklisted",IF(AND(P7>=100000,Q7>=4,O7<=10%,V7="Completed"),"Platinum",IF(AND(P7>=50000,P7<100000,Q7>=3,V7="Completed"),"Gold",IF(AND(P7<50000,V7="Completed"),"Silver","Blacklisted")))) -> Blacklisted
A8: ORD10007 | B8: C008 | C8: P201 | D8: 31/02/2025 | E8: 25/02/2026 | F8: Kavya Nair | G8: Female | H8: 20/03/2003 | I8: Hyderabad | J8: South | K8: Home Appliances | L8: Mixer | M8: 2 | N8: 3500 | O8: 5 | P8: 6650 | Q8: 1 | R8: UPI | S8: Ritika | T8: kavya.nair@company.com | U8: 9958252176 | V8: Completed | W8: =IF(OR(Q8<=2,V8="Cancelled"),"Blacklisted",IF(AND(P8>=100000,Q8>=4,O8<=10%,V8="Completed"),"Platinum",IF(AND(P8>=50000,P8<100000,Q8>=3,V8="Completed"),"Gold",IF(AND(P8<50000,V8="Completed"),"Silver","Blacklisted")))) -> Blacklisted
A9: ORD10008 | B9: C002 | C9: P104 | D9: 13/04/2025 | E9: 19/04/2025 | F9: Priya Patel | G9: Female | H9: 07/03/1995 | I9: Mumbai | J9: West | K9: Electronics | L9: Monitor | M9: 14 | N9: 12000 | O9: 15 | P9: 142800 | Q9: 4 | R9: NetBanking | S9: Ritika | T9: priYa.patel@company.com | U9: 9705521654 | V9: Completed | W9: =IF(OR(Q9<=2,V9="Cancelled"),"Blacklisted",IF(AND(P9>=100000,Q9>=4,O9<=10%,V9="Completed"),"Platinum",IF(AND(P9>=50000,P9<100000,Q9>=3,V9="Completed"),"Gold",IF(AND(P9<50000,V9="Completed"),"Silver","Blacklisted")))) -> Blacklisted
A10: ORD10009 | B10: C008 | C10: P104 | D10: 31/01/2026 | E10: 02/02/2026 | F10: kavya Nair | G10: Female | H10: 06/04/1997 | I10: Pune | J10: West | K10: Electronics | L10: Monitor | M10: 4 | N10: 12000 | O10: 15 | P10: 40800 | Q10: 4 | R10: UPI | S10: Neha | T10: kavya.nair@company.com | U10: 9588041011 | V10: Completed | W10: =IF(OR(Q10<=2,V10="Cancelled"),"Blacklisted",IF(AND(P10>=100000,Q10>=4,O10<=10%,V10="Completed"),"Platinum",IF(AND(P10>=50000,P10<100000,Q10>=3,V10="Completed"),"Gold",IF(AND(P10<50000,V10="Completed"),"Silver","Blacklisted")))) -> Silver
A11: ORD10010 | B11: C002 | C11: P301 | D11: 25/03/2025 | E11: 27/03/2025 | F11: Priya Patel | G11: Female | H11: 07/01/1990 | I11: Mumbai | J11: West | K11: Stationery | L11: Notebook | M11: 6 | N11: 60 | O11: 0 | P11: 360 | Q11: 4 | R11: Card | S11: Neha | T11: PRiya.patel@company.com | U11: 9340540608 | V11: Completed | W11: =IF(OR(Q11<=2,V11="Cancelled"),"Blacklisted",IF(AND(P11>=100000,Q11>=4,O11<=10%,V11="Completed"),"Platinum",IF(AND(P11>=50000,P11<100000,Q11>=3,V11="Completed"),"Gold",IF(AND(P11<50000,V11="Completed"),"Silver","Blacklisted")))) -> Silver
A12: ORD10011 | B12: C003 | C12: P202 | D12: 19/09/2025 | E12: 23/09/2025 | F12: Rohit Singh | G12: Male | H12: 10/05/1982 | I12: Delhi | J12: North | K12: Home Appliances | L12: Iron | M12: -3 | N12: 2200 | O12: 0 | P12: 35200 | Q12: 2 | R12: Card | S12: Rahul | T12: rohit.singh@company.com | U12: 9521710321 | V12: Pending | W12: =IF(OR(Q12<=2,V12="Cancelled"),"Blacklisted",IF(AND(P12>=100000,Q12>=4,O12<=10%,V12="Completed"),"Platinum",IF(AND(P12>=50000,P12<100000,Q12>=3,V12="Completed"),"Gold",IF(AND(P12<50000,V12="Completed"),"Silver","Blacklisted")))) -> Blacklisted
A13: ORD10012 | B13: C008 | C13: P201 | D13: 08/03/2025 | E13: 15/03/2025 | F13: Kavya Nair | G13: Female | H13: 23/01/1982 | I13: Ahmedabad | J13: West | K13: Home Appliances | L13: Mixer | M13: 10 | N13: 3500 | O13: 5 | P13: 33250 | Q13: 5 | R13: Card | S13: Aisha | T13: kavya.nair@company.com | U13: 9123535241 | V13: Cancelled | W13: =IF(OR(Q13<=2,V13="Cancelled"),"Blacklisted",IF(AND(P13>=100000,Q13>=4,O13<=10%,V13="Completed"),"Platinum",IF(AND(P13>=50000,P13<100000,Q13>=3,V13="Completed"),"Gold",IF(AND(P13<50000,V13="Completed"),"Silver","Blacklisted")))) -> Blacklisted
... A39: ORD10038 | B39: C006 | C39: P201 | D39: 08/03/2026 | E39: 20/03/2026 | F39: Sneha Joshi | G39: Female | H39: 21/06/1980 | I39: Delhi | J39: North | K39: Home Appliances | L39: Mixer | M39: 20 | N39: 3500 | O39: 10 | P39: 63000 | Q39: 3 | R39: Card | S39: Rahul | T39: sneha.joshi@company.com | U39: 9283578533 | V39: Cancelled | W39: =IF(OR(Q39<=2,V39="Cancelled"),"Blacklisted",IF(AND(P39>=100000,Q39>=4,O39<=10%,V39="Completed"),"Platinum",IF(AND(P39>=50000,P39<100000,Q39>=3,V39="Completed"),"Gold",IF(AND(P39<50000,V39="Completed"),"Silver","Blacklisted")))) -> Blacklisted
A40: ORD10039 | B40: C008 | C40: P302 | D40: 13/02/2025 | E40: 19/02/2025 | F40: Kavya Nair | G40: Female | H40: 17/06/1979 | I40: Pune | J40: West | K40: Stationery | L40: Pen | M40: 5 | N40: 1200 | O40: 0 | P40: 100 | Q40: 1 | R40: Cash | S40: Rahul | T40: kavya.nair@company.com | U40: 9963005771 | V40: Cancelled | W40: =IF(OR(Q40<=2,V40="Cancelled"),"Blacklisted",IF(AND(P40>=100000,Q40>=4,O40<=10%,V40="Completed"),"Platinum",IF(AND(P40>=50000,P40<100000,Q40>=3,V40="Completed"),"Gold",IF(AND(P40<50000,V40="Completed"),"Silver","Blacklisted")))) -> Blacklisted
A41: ORD10040 | B41: C010 | C41: P203 | D41: 05/10/2025 | E41: 15/10/2025 | F41: Pooja Shah | G41: Female | H41: 18/06/1992 | I41: Mumbai | J41: West | K41: Home Appliances | L41: Microwave | M41: 20 | N41: 8500 | O41: 0 | P41: 170000 | Q41: 1 | R41: UPI | S41: Neha | T41: pooja.shah@company.com | U41: 9484632635 | V41: Cancelled | W41: =IF(OR(Q41<=2,V41="Cancelled"),"Blacklisted",IF(AND(P41>=100000,Q41>=4,O41<=10%,V41="Completed"),"Platinum",IF(AND(P41>=50000,P41<100000,Q41>=3,V41="Completed"),"Gold",IF(AND(P41<50000,V41="Completed"),"Silver","Blacklisted")))) -> Blacklisted
A42: ORD10041 | B42: C007 | C42: P301 | D42: 10/02/2026 | E42: 12/02/2026 | F42: Arjun Rao | G42: Male | H42: 06/06/1994 | I42: Bengaluru | J42: South | K42: Stationery | L42: Notebook | M42: 8 | N42: 60 | O42: 15 | P42: 408 | Q42: 5 | R42: UPI | S42: Rahul | T42: arjun.rao@company.com | U42: 9276319484 | V42: Pending | W42: =IF(OR(Q42<=2,V42="Cancelled"),"Blacklisted",IF(AND(P42>=100000,Q42>=4,O42<=10%,V42="Completed"),"Platinum",IF(AND(P42>=50000,P42<100000,Q42>=3,V42="Completed"),"Gold",IF(AND(P42<50000,V42="Completed"),"Silver","Blacklisted")))) -> Blacklisted
A43: ORD10042 | B43: C010 | C43: P201 | D43: 04/06/2025 | E43: 16/06/2025 | F43: Pooja Shah | G43: Female | H43: 22/09/1988 | I43: Pune | J43: West | K43: Home Appliances | L43: Mixer | M43: 8 | N43: 3500 | O43: 5 | P43: 26600 | Q43: 1 | R43: Card | S43: Neha | T43: pooja.shah@company.com | U43: 9619034852 | V43: Pending | W43: =IF(OR(Q43<=2,V43="Cancelled"),"Blacklisted",IF(AND(P43>=100000,Q43>=4,O43<=10%,V43="Completed"),"Platinum",IF(AND(P43>=50000,P43<100000,Q43>=3,V43="Completed"),"Gold",IF(AND(P43<50000,V43="Completed"),"Silver","Blacklisted")))) -> Blacklisted
A44: ORD10043 | B44: C009 | C44: P203 | D44: 08/02/2026 | E44: 14/02/2026 | F44: Mohit Verma | G44: Male | H44: 14/07/2001 | I44: Jaipur | J44: North | K44: Home Appliances | L44: Microwave | M44: 1 | N44: 8500 | O44: 0 | P44: 8500 | Q44: 2 | R44: Card | S44: Neha | T44: mohit.verma@company.com | U44: 9636416962 | V44: Pending | W44: =IF(OR(Q44<=2,V44="Cancelled"),"Blacklisted",IF(AND(P44>=100000,Q44>=4,O44<=10%,V44="Completed"),"Platinum",IF(AND(P44>=50000,P44<100000,Q44>=3,V44="Completed"),"Gold",IF(AND(P44<50000,V44="Completed"),"Silver","Blacklisted")))) -> Blacklisted
A45: ORD10044 | B45: C001 | C45: P303 | D45: 30/03/2025 | E45: 31/03/2025 | F45: amit Sharma | G45: Male | H45: 09/08/1991 | I45: Pune | J45: West | K45: Stationery | L45: Marker | M45: 8 | N45: 45 | O45: 15 | P45: 306 | Q45: 2 | R45: Card | S45: Aisha | T45: amit.sharma@company.com | U45: 9357133880 | V45: Completed | W45: =IF(OR(Q45<=2,V45="Cancelled"),"Blacklisted",IF(AND(P45>=100000,Q45>=4,O45<=10%,V45="Completed"),"Platinum",IF(AND(P45>=50000,P45<100000,Q45>=3,V45="Completed"),"Gold",IF(AND(P45<50000,V45="Completed"),"Silver","Blacklisted")))) -> Blacklisted
A46: ORD10045 | B46: C006 | C46: P202 | D46: 25/04/2025 | E46: 28/04/2025 | F46: Sneha Joshi | G46: Female | H46: 21/10/1988 | I46: Pune | J46: West | K46: Home Appliances | L46: Iron | M46: 16 | N46: 2200 | O46: 5 | P46: 33440 | Q46: 5 | R46: Card | S46: Aisha | T46: sneha.joshi@company.com | U46: 9575210324 | V46: Cancelled | W46: =IF(OR(Q46<=2,V46="Cancelled"),"Blacklisted",IF(AND(P46>=100000,Q46>=4,O46<=10%,V46="Completed"),"Platinum",IF(AND(P46>=50000,P46<100000,Q46>=3,V46="Completed"),"Gold",IF(AND(P46<50000,V46="Completed"),"Silver","Blacklisted")))) -> Blacklisted
A47: ORD10046 | B47: C009 | C47: P201 | D47: 13/10/2025 | E47: 23/10/2025 | F47: Mohit Verma | G47: Male | H47: 19/11/2002 | I47: Bengaluru | J47: South | K47: Home Appliances | L47: Mixer | M47: 19 | N47: 3500 | O47: 20 | P47: 53200 | Q47: 3 | R47: Cash | S47: Karan | T47: mohit.verma@company.com | U47: 9276080204 | V47: Cancelled | W47: =IF(OR(Q47<=2,V47="Cancelled"),"Blacklisted",IF(AND(P47>=100000,Q47>=4,O47<=10%,V47="Completed"),"Platinum",IF(AND(P47>=50000,P47<100000,Q47>=3,V47="Completed"),"Gold",IF(AND(P47<50000,V47="Completed"),"Silver","Blacklisted")))) -> Blacklisted
A48: ORD10047 | B48: C006 | C48: P102 | D48: 11/10/2025 | E48: 14/10/2025 | F48: Sneha Joshi | G48: Female | H48: 06/07/2000 | I48: Pune | J48: West | K48: Electronics | L48: Mouse | M48: 15 | N48: 700 | O48: 15 | P48: 8925 | Q48: 4 | R48: UPI | S48: Neha | T48: sneha.joshicompany.com | U48: 9856624471 | V48: Completed | W48: =IF(OR(Q48<=2,V48="Cancelled"),"Blacklisted",IF(AND(P48>=100000,Q48>=4,O48<=10%,V48="Completed"),"Platinum",IF(AND(P48>=50000,P48<100000,Q48>=3,V48="Completed"),"Gold",IF(AND(P48<50000,V48="Completed"),"Silver","Blacklisted")))) -> Silver
A49: ORD10048 | B49: C006 | C49: P102 | D49: 27/11/2025 | E49: 03/12/2025 | F49: Sneha Joshi | G49: Female | H49: 26/11/1998 | I49: Jaipur | J49: North | K49: Electronics | L49: Mouse | M49: 19 | N49: 700 | O49: 20 | P49: 10640 | Q49: 1 | R49: Cash | S49: Neha | T49: sneha.joshi@company.com | U49: 9238141322 | V49: Completed | W49: =IF(OR(Q49<=2,V49="Cancelled"),"Blacklisted",IF(AND(P49>=100000,Q49>=4,O49<=10%,V49="Completed"),"Platinum",IF(AND(P49>=50000,P49<100000,Q49>=3,V49="Completed"),"Gold",IF(AND(P49<50000,V49="Completed"),"Silver","Blacklisted")))) -> Blacklisted
A50: ORD10049 | B50: C009 | C50: P104 | D50: 19/04/2026 | F50: Mohit Verma | G50: Male | H50: 03/06/1996 | I50: Delhi | J50: North | K50: Electronics | L50: Monitor | M50: 19 | N50: 12000 | O50: 0 | P50: 228000 | Q50: 1 | R50: NetBanking | S50: Aisha | T50: mohit.verma@company.com | U50: 9890380030 | V50: Completed | W50: =IF(OR(Q50<=2,V50="Cancelled"),"Blacklisted",IF(AND(P50>=100000,Q50>=4,O50<=10%,V50="Completed"),"Platinum",IF(AND(P50>=50000,P50<100000,Q50>=3,V50="Completed"),"Gold",IF(AND(P50<50000,V50="Completed"),"Silver","Blacklisted")))) -> Blacklisted
A51: ORD10050 | B51: C004 | C51: P103 | D51: 19/04/2026 | E51: 21/04/2026 | F51: Anita Gupta | G51: Female | H51: 15/03/1987 | I51: Pune | J51: West | K51: Electronics | L51: Keyboard | M51: 6 | N51: 1200 | O51: 5 | P51: 6840 | Q51: 2 | R51: Cash | S51: Ritika | T51: anita.gupta@company.com | U51: 9495893170 | V51: Pending | W51: =IF(OR(Q51<=2,V51="Cancelled"),"Blacklisted",IF(AND(P51>=100000,Q51>=4,O51<=10%,V51="Completed"),"Platinum",IF(AND(P51>=50000,P51<100000,Q51>=3,V51="Completed"),"Gold",IF(AND(P51<50000,V51="Completed"),"Silver","Blacklisted")))) -> Blacklisted
A52: ORD10051 | B52: C010 | C52: P202 | D52: 28/03/2025 | E52: 07/04/2025 | F52: POoja Shah | G52: Female | H52: 20/02/1979 | I52: Bengaluru | J52: South | K52: Home Appliances | L52: Iron | M52: 7 | N52: 2200 | O52: 15 | P52: 13090 | Q52: 1 | R52: UPI | S52: Aisha | T52: pooja.shah@company.com | U52: 9485166307 | V52: Completed | W52: =IF(OR(Q52<=2,V52="Cancelled"),"Blacklisted",IF(AND(P52>=100000,Q52>=4,O52<=10%,V52="Completed"),"Platinum",IF(AND(P52>=50000,P52<100000,Q52>=3,V52="Completed"),"Gold",IF(AND(P52<50000,V52="Completed"),"Silver","Blacklisted")))) -> Blacklisted
A53: ORD10052 | B53: C002 | C53: P301 | D53: 25/08/2025 | E53: 28/08/2025 | F53: Priya Patel | G53: Female | H53: 09/08/2000 | I53: Jaipur | J53: North | K53: Stationery | L53: Notebook | M53: 8 | N53: 60 | O53: 10 | P53: 432 | Q53: 5 | R53: Card | S53: Aisha | T53: priya.patel@company.com | U53: 9924709648 | V53: Cancelled | W53: =IF(OR(Q53<=2,V53="Cancelled"),"Blacklisted",IF(AND(P53>=100000,Q53>=4,O53<=10%,V53="Completed"),"Platinum",IF(AND(P53>=50000,P53<100000,Q53>=3,V53="Completed"),"Gold",IF(AND(P53<50000,V53="Completed"),"Silver","Blacklisted")))) -> Blacklisted
A54: ORD10053 | B54: C005 | C54: P101 | D54: 19/08/2025 | E54: 23/08/2025 | F54: Vikas Mehta | G54: Male | H54: 17/01/1976 | I54: Kolkata | J54: East | K54: Electronics | L54: Laptop | M54: 12 | N54: 55000 | O54: 5 | P54: 627000 | Q54: 2 | R54: UPI | S54: Rahul | T54: vikas.mehta@company.com | U54: 9350554626 | V54: Pending | W54: =IF(OR(Q54<=2,V54="Cancelled"),"Blacklisted",IF(AND(P54>=100000,Q54>=4,O54<=10%,V54="Completed"),"Platinum",IF(AND(P54>=50000,P54<100000,Q54>=3,V54="Completed"),"Gold",IF(AND(P54<50000,V54="Completed"),"Silver","Blacklisted")))) -> Blacklisted
A55: ORD10054 | B55: C008 | C55: P102 | D55: 27/07/2025 | E55: 05/08/2025 | F55: Kavya Nair | G55: Female | H55: 04/04/1975 | I55: Jaipur | J55: North | K55: Electronics | L55: Mouse | M55: 3 | N55: 700 | O55: 0 | P55: 2100 | Q55: 3 | R55: Card | S55: Karan | T55: kavya.nair@company.com | U55: 9743295580 | V55: Cancelled | W55: =IF(OR(Q55<=2,V55="Cancelled"),"Blacklisted",IF(AND(P55>=100000,Q55>=4,O55<=10%,V55="Completed"),"Platinum",IF(AND(P55>=50000,P55<100000,Q55>=3,V55="Completed"),"Gold",IF(AND(P55<50000,V55="Completed"),"Silver","Blacklisted")))) -> Blacklisted
A56: ORD10055 | B56: C003 | C56: P301 | D56: 21/02/2025 | E56: 26/02/2025 | F56: RoHit Singh | G56: Male | H56: 11/12/1976 | I56: Ahmedabad | J56: West | K56: Stationery | L56: Notebook | M56: 19 | N56: 60 | O56: 15 | P56: 969 | Q56: 4 | R56: Card | S56: Rahul | T56: rohit.singh@company.com | U56: 9822926495 | V56: Cancelled | W56: =IF(OR(Q56<=2,V56="Cancelled"),"Blacklisted",IF(AND(P56>=100000,Q56>=4,O56<=10%,V56="Completed"),"Platinum",IF(AND(P56>=50000,P56<100000,Q56>=3,V56="Completed"),"Gold",IF(AND(P56<50000,V56="Completed"),"Silver","Blacklisted")))) -> Blacklisted
A57: ORD10056 | B57: C001 | C57: P301 | D57: 10/08/2025 | E57: 11/08/2025 | F57: Amit Sharma | G57: Male | H57: 03/12/1979 | I57: Jaipur | J57: North | K57: Stationery | L57: Notebook | M57: 9 | N57: 60 | O57: 20 | P57: 432 | Q57: 1 | R57: NetBanking | S57: Neha | T57: amit.sharma@company.com | U57: 9518298190 | V57: Pending | W57: =IF(OR(Q57<=2,V57="Cancelled"),"Blacklisted",IF(AND(P57>=100000,Q57>=4,O57<=10%,V57="Completed"),"Platinum",IF(AND(P57>=50000,P57<100000,Q57>=3,V57="Completed"),"Gold",IF(AND(P57<50000,V57="Completed"),"Silver","Blacklisted")))) -> Blacklisted
A58: ORD10057 | B58: C001 | C58: P102 | D58: 24/03/2026 | E58: 30/03/2026 | F58: Amit Sharma | G58: Male | H58: 27/12/1978 | I58: Bengaluru | J58: South | K58: Electronics | L58: Mouse | M58: 6 | N58: 700 | O58: 0 | P58: 4200 | Q58: 4 | R58: UPI | S58: Rahul | T58: amit.sharmcompany.com | U58: 9366223547 | V58: Cancelled | W58: =IF(OR(Q58<=2,V58="Cancelled"),"Blacklisted",IF(AND(P58>=100000,Q58>=4,O58<=10%,V58="Completed"),"Platinum",IF(AND(P58>=50000,P58<100000,Q58>=3,V58="Completed"),"Gold",IF(AND(P58<50000,V58="Completed"),"Silver","Blacklisted")))) -> Blacklisted
A59: ORD10058 | B59: C003 | C59: P303 | D59: 13/03/2026 | E59: 19/03/2026 | F59: Rohit Singh | G59: Male | H59: 15/04/1975 | I59: Delhi | J59: North | K59: Stationery | L59: Marker | M59: 18 | N59: 45 | O59: 5 | P59: 769.5 | Q59: 1 | R59: Card | S59: Aisha | T59: rohit.singh@company.com | U59: 9701988524 | V59: Pending | W59: =IF(OR(Q59<=2,V59="Cancelled"),"Blacklisted",IF(AND(P59>=100000,Q59>=4,O59<=10%,V59="Completed"),"Platinum",IF(AND(P59>=50000,P59<100000,Q59>=3,V59="Completed"),"Gold",IF(AND(P59<50000,V59="Completed"),"Silver","Blacklisted")))) -> Blacklisted
A60: ORD10059 | B60: C007 | C60: P302 | D60: 15/06/2025 | E60: 26/06/2025 | F60: Arjun Rao | G60: Male | H60: 19/12/1988 | I60: Jaipur | J60: North | K60: Stationery | L60: Pen | M60: 8 | N60: 20 | O60: 5 | P60: 152 | Q60: 1 | R60: Card | S60: Ritika | T60: arjun.rao@company.com | U60: 9836327649 | V60: completed | W60: =IF(OR(Q60<=2,V60="Cancelled"),"Blacklisted",IF(AND(P60>=100000,Q60>=4,O60<=10%,V60="Completed"),"Platinum",IF(AND(P60>=50000,P60<100000,Q60>=3,V60="Completed"),"Gold",IF(AND(P60<50000,V60="Completed"),"Silver","Blacklisted")))) -> Blacklisted
A61: ORD10060 | B61: C005 | C61: P102 | D61: 05/03/2025 | E61: 06/03/2025 | F61: Vikas Mehta | G61: Male | H61: 07/03/1979 | I61: Jaipur | J61: North | K61: Electronics | L61: Mouse | M61: 8 | N61: 700 | O61: 10 | P61: 5040 | Q61: 1 | R61: NetBanking | S61: Aisha | T61: Vikas.mehta@company.com | U61: 9261800516 | V61: Cancelled | W61: =IF(OR(Q61<=2,V61="Cancelled"),"Blacklisted",IF(AND(P61>=100000,Q61>=4,O61<=10%,V61="Completed"),"Platinum",IF(AND(P61>=50000,P61<100000,Q61>=3,V61="Completed"),"Gold",IF(AND(P61<50000,V61="Completed"),"Silver","Blacklisted")))) -> Blacklisted
A62: ORD10061 | B62: C008 | C62: P302 | D62: 09/04/2026 | E62: 19/04/2026 | F62: Kavya Nair | G62: Female | H62: 17/12/2003 | I62: Delhi | J62: North | K62: Stationery | L62: Pen | M62: 7 | N62: 20 | O62: 15 | P62: 119 | Q62: 5 | R62: Card | S62: Rahul | T62: kavya.nair@company.com | U62: 9950802015 | V62: Completed | W62: =IF(OR(Q62<=2,V62="Cancelled"),"Blacklisted",IF(AND(P62>=100000,Q62>=4,O62<=10%,V62="Completed"),"Platinum",IF(AND(P62>=50000,P62<100000,Q62>=3,V62="Completed"),"Gold",IF(AND(P62<50000,V62="Completed"),"Silver","Blacklisted")))) -> Silver
... A74: ORD10073 | B74: C008 | C74: P103 | D74: 13/12/2025 | E74: 23/12/2025 | F74: Kavya Nair | G74: Female | H74: 22/09/1981 | I74: Jaipur | J74: North | K74: Electronics | L74: Keyboard | M74: 1 | N74: 1200 | O74: 5 | P74: 1140 | Q74: 3 | R74: UPI | S74: Aisha | T74: kavya.nair@company.com | U74: 9808988530 | V74: Cancelled | W74: =IF(OR(Q74<=2,V74="Cancelled"),"Blacklisted",IF(AND(P74>=100000,Q74>=4,O74<=10%,V74="Completed"),"Platinum",IF(AND(P74>=50000,P74<100000,Q74>=3,V74="Completed"),"Gold",IF(AND(P74<50000,V74="Completed"),"Silver","Blacklisted")))) -> Blacklisted
A75: ORD10074 | B75: C010 | C75: P202 | D75: 04/02/2026 | E75: 16/02/2026 | F75: Pooja Shah | G75: Female | H75: 20/06/1980 | J75: South | K75: Home Appliances | L75: Iron | M75: 1 | N75: 2200 | O75: 15 | P75: 1870 | Q75: 4 | R75: Card | S75: Aisha | T75: pooja.shah@company.com | U75: 9286410494 | V75: Completed | W75: =IF(OR(Q75<=2,V75="Cancelled"),"Blacklisted",IF(AND(P75>=100000,Q75>=4,O75<=10%,V75="Completed"),"Platinum",IF(AND(P75>=50000,P75<100000,Q75>=3,V75="Completed"),"Gold",IF(AND(P75<50000,V75="Completed"),"Silver","Blacklisted")))) -> Silver
A76: ORD10075 | B76: C003 | C76: P103 | D76: 26/01/2026 | E76: 28/01/2026 | F76: Rohit Singh | G76: Male | H76: 02/11/1982 | I76: Pune | J76: West | K76: Electronics | L76: Keyboard | M76: 3 | N76: 1200 | O76: 10 | P76: 3240 | Q76: 5 | R76: Cash | S76: Rahul | T76: rohit.singh@company.com | U76: 9311555196 | V76: Completed | W76: =IF(OR(Q76<=2,V76="Cancelled"),"Blacklisted",IF(AND(P76>=100000,Q76>=4,O76<=10%,V76="Completed"),"Platinum",IF(AND(P76>=50000,P76<100000,Q76>=3,V76="Completed"),"Gold",IF(AND(P76<50000,V76="Completed"),"Silver","Blacklisted")))) -> Silver
A77: ORD10076 | B77: C008 | C77: P201 | D77: 27/06/2025 | E77: 07/07/2025 | F77: Kavya Nair | G77: Female | H77: 10/01/1980 | I77: Bengaluru | J77: South | K77: Home Appliances | L77: Mixer | M77: 10 | N77: 3500 | O77: 20 | P77: 28000 | Q77: 5 | R77: Card | S77: Ritika | T77: kavya.nair@company.com | U77: 9101810266 | V77: Completed | W77: =IF(OR(Q77<=2,V77="Cancelled"),"Blacklisted",IF(AND(P77>=100000,Q77>=4,O77<=10%,V77="Completed"),"Platinum",IF(AND(P77>=50000,P77<100000,Q77>=3,V77="Completed"),"Gold",IF(AND(P77<50000,V77="Completed"),"Silver","Blacklisted")))) -> Silver
A78: ORD10077 | B78: C007 | C78: P102 | D78: 17/03/2026 | E78: 19/03/2026 | F78: Arjun Rao | G78: Male | H78: 27/04/1981 | I78: Delhi | J78: North | K78: Electronics | L78: Mouse | M78: 18 | N78: 700 | O78: 5 | P78: 11970 | Q78: 3 | R78: Card | S78: Neha | T78: arjun.rao@company.com | U78: 9464556593 | V78: Cancelled | W78: =IF(OR(Q78<=2,V78="Cancelled"),"Blacklisted",IF(AND(P78>=100000,Q78>=4,O78<=10%,V78="Completed"),"Platinum",IF(AND(P78>=50000,P78<100000,Q78>=3,V78="Completed"),"Gold",IF(AND(P78<50000,V78="Completed"),"Silver","Blacklisted")))) -> Blacklisted
A79: ORD10078 | B79: C005 | C79: P102 | D79: 09/06/2025 | E79: 18/06/2025 | F79: Vikas Mehta | G79: Male | H79: 12/03/1985 | I79: Bengaluru | J79: South | K79: Electronics | L79: Mouse | M79: 12 | N79: 700 | O79: 15 | P79: 7140 | Q79: 2 | R79: UPI | S79: Rahul | T79: vikas.mehta@company.com | U79: 9338278358 | V79: Completed | W79: =IF(OR(Q79<=2,V79="Cancelled"),"Blacklisted",IF(AND(P79>=100000,Q79>=4,O79<=10%,V79="Completed"),"Platinum",IF(AND(P79>=50000,P79<100000,Q79>=3,V79="Completed"),"Gold",IF(AND(P79<50000,V79="Completed"),"Silver","Blacklisted")))) -> Blacklisted
A80: ORD10079 | B80: C009 | C80: P103 | D80: 15/11/2025 | E80: 16/11/2025 | F80: Mohit Verma | G80: Male | H80: 15/03/1999 | I80: Mumbai | J80: West | K80: Electronics | L80: Keyboard | M80: 8 | N80: 1200 | O80: 0 | P80: 9600 | Q80: 4 | R80: Card | S80: Rahul | T80: mohit.verma@company.com | U80: 9621410770 | V80: Pending | W80: =IF(OR(Q80<=2,V80="Cancelled"),"Blacklisted",IF(AND(P80>=100000,Q80>=4,O80<=10%,V80="Completed"),"Platinum",IF(AND(P80>=50000,P80<100000,Q80>=3,V80="Completed"),"Gold",IF(AND(P80<50000,V80="Completed"),"Silver","Blacklisted")))) -> Blacklisted
A81: ORD10080 | B81: C003 | C81: P301 | D81: 06/11/2025 | E81: 10/11/2025 | F81: Rohit Singh | G81: Male | H81: 07/07/1983 | I81: Pune | J81: West | K81: Stationery | L81: Notebook | M81: 2 | N81: 60 | O81: 0 | P81: 120 | Q81: 2 | R81: UPI | S81: Rahul | T81: rohit.singh@company.com | U81: 9981333189 | V81: Completed | W81: =IF(OR(Q81<=2,V81="Cancelled"),"Blacklisted",IF(AND(P81>=100000,Q81>=4,O81<=10%,V81="Completed"),"Platinum",IF(AND(P81>=50000,P81<100000,Q81>=3,V81="Completed"),"Gold",IF(AND(P81<50000,V81="Completed"),"Silver","Blacklisted")))) -> Blacklisted
A82: ORD10081 | B82: C001 | C82: P303 | D82: 01/01/2025 | E82: 07/01/2025 | F82: Amit Sharma | G82: Male | H82: 06/03/1989 | I82: Pune | J82: West | K82: Stationery | L82: Marker | M82: 10 | N82: 45 | O82: 15 | P82: 382.5 | Q82: 3 | R82: NetBanking | S82: Ritika | T82: amit.sharma@company.com | U82: 9723450355 | V82: Cancelled | W82: =IF(OR(Q82<=2,V82="Cancelled"),"Blacklisted",IF(AND(P82>=100000,Q82>=4,O82<=10%,V82="Completed"),"Platinum",IF(AND(P82>=50000,P82<100000,Q82>=3,V82="Completed"),"Gold",IF(AND(P82<50000,V82="Completed"),"Silver","Blacklisted")))) -> Blacklisted
A83: ORD10082 | B83: C005 | C83: P201 | D83: 25/04/2026 | E83: 03/05/2026 | F83: Vikas Mehta | G83: Male | H83: 20/06/1982 | I83: Kolkata | J83: East | K83: Home Appliances | L83: Mixer | M83: 12 | N83: 3500 | O83: 5 | P83: 39900 | Q83: 3 | R83: NetBanking | S83: Aisha | T83: vikas.mehta@company.com | U83: 9886243907 | V83: Pending | W83: =IF(OR(Q83<=2,V83="Cancelled"),"Blacklisted",IF(AND(P83>=100000,Q83>=4,O83<=10%,V83="Completed"),"Platinum",IF(AND(P83>=50000,P83<100000,Q83>=3,V83="Completed"),"Gold",IF(AND(P83<50000,V83="Completed"),"Silver","Blacklisted")))) -> Blacklisted
A84: ORD10083 | B84: C003 | C84: P301 | D84: 19/09/2025 | E84: 27/09/2025 | F84: Rohit Singh | G84: Male | H84: 23/06/2001 | I84: Mumbai | J84: West | K84: Stationery | L84: Notebook | M84: 2 | N84: 60 | O84: 15 | P84: 102 | Q84: 1 | R84: UPI | S84: Neha | T84: rohit.singh@company.com | U84: 9473931904 | V84: Completed | W84: =IF(OR(Q84<=2,V84="Cancelled"),"Blacklisted",IF(AND(P84>=100000,Q84>=4,O84<=10%,V84="Completed"),"Platinum",IF(AND(P84>=50000,P84<100000,Q84>=3,V84="Completed"),"Gold",IF(AND(P84<50000,V84="Completed"),"Silver","Blacklisted")))) -> Blacklisted
A85: ORD10084 | B85: C003 | C85: P103 | D85: 18/03/2025 | E85: 21/03/2025 | F85: Rohit Singh | G85: Male | H85: 19/07/1983 | I85: Hyderabad | J85: South | K85: Electronics | L85: Keyboard | M85: 18 | N85: 1200 | O85: 15 | P85: 18360 | Q85: 3 | R85: Card | S85: Neha | T85: rohit.singh@company.com | U85: 9287159610 | V85: Pending | W85: =IF(OR(Q85<=2,V85="Cancelled"),"Blacklisted",IF(AND(P85>=100000,Q85>=4,O85<=10%,V85="Completed"),"Platinum",IF(AND(P85>=50000,P85<100000,Q85>=3,V85="Completed"),"Gold",IF(AND(P85<50000,V85="Completed"),"Silver","Blacklisted")))) -> Blacklisted
A86: ORD10085 | B86: C008 | C86: P104 | D86: 30/10/2025 | E86: 31/10/2025 | F86: Kavya Nair | G86: Female | H86: 24/03/1993 | I86: Mumbai | J86: West | K86: Electronics | L86: Monitor | M86: 18 | N86: 12000 | O86: 15 | P86: 183600 | Q86: 2 | R86: Cash | S86: Rahul | T86: kavya.nair@company.com | U86: 9876513858 | V86: Completed | W86: =IF(OR(Q86<=2,V86="Cancelled"),"Blacklisted",IF(AND(P86>=100000,Q86>=4,O86<=10%,V86="Completed"),"Platinum",IF(AND(P86>=50000,P86<100000,Q86>=3,V86="Completed"),"Gold",IF(AND(P86<50000,V86="Completed"),"Silver","Blacklisted")))) -> Blacklisted
A87: ORD10086 | B87: C007 | C87: P302 | D87: 31/10/2025 | E87: 11/11/2025 | F87: Arjun Rao | G87: Male | H87: 10/05/1995 | I87: Ahmedabad | J87: West | K87: Stationery | L87: Pen | M87: 7 | N87: 20 | O87: 0 | P87: 140 | Q87: 2 | R87: Card | S87: Ritika | T87: arjun.rao@company.com | U87: 9237400853 | V87: Cancelled | W87: =IF(OR(Q87<=2,V87="Cancelled"),"Blacklisted",IF(AND(P87>=100000,Q87>=4,O87<=10%,V87="Completed"),"Platinum",IF(AND(P87>=50000,P87<100000,Q87>=3,V87="Completed"),"Gold",IF(AND(P87<50000,V87="Completed"),"Silver","Blacklisted")))) -> Blacklisted
... A119: ORD10118 | B119: C001 | C119: P303 | D119: 31/05/2025 | E119: 11/06/2025 | F119: Amit Sharma | G119: Male | H119: 07/09/1995 | I119: Pune | J119: West | K119: Stationery | L119: Marker | M119: 16 | N119: 45 | O119: 0 | P119: 720 | Q119: 1 | R119: NetBanking | S119: Aisha | T119: amit.sharma@company.com | U119: 9807154421 | V119: Completed | W119: =IF(OR(Q119<=2,V119="Cancelled"),"Blacklisted",IF(AND(P119>=100000,Q119>=4,O119<=10%,V119="Completed"),"Platinum",IF(AND(P119>=50000,P119<100000,Q119>=3,V119="Completed"),"Gold",IF(AND(P119<50000,V119="Completed"),"Silver","Blacklisted")))) -> Blacklisted
A120: ORD10119 | B120: C009 | C120: P103 | D120: 30/05/2025 | E120: 02/06/2025 | F120: Mohit Verma | G120: Male | H120: 08/03/1988 | I120: Ahmedabad | J120: West | K120: Electronics | L120: Keyboard | M120: Ten | N120: 1200 | O120: 15 | P120: 7140 | Q120: 4 | R120: UPI | S120: Karan | T120: mohit.verma@company.com | U120: 9919834000 | V120: Pending | W120: =IF(OR(Q120<=2,V120="Cancelled"),"Blacklisted",IF(AND(P120>=100000,Q120>=4,O120<=10%,V120="Completed"),"Platinum",IF(AND(P120>=50000,P120<100000,Q120>=3,V120="Completed"),"Gold",IF(AND(P120<50000,V120="Completed"),"Silver","Blacklisted")))) -> Blacklisted
A121: ORD10120 | B121: C002 | C121: P104 | D121: 19/08/2025 | E121: 30/08/2025 | F121: Priya Patel | G121: Female | H121: 07/07/1989 | I121: Jaipur | J121: North | K121: Electronics | L121: Monitor | M121: 14 | N121: 12000 | O121: 15 | P121: 142800 | Q121: 2 | R121: NetBanking | S121: Aisha | T121: priya.patel@company.com | U121: 9739798818 | V121: Pending | W121: =IF(OR(Q121<=2,V121="Cancelled"),"Blacklisted",IF(AND(P121>=100000,Q121>=4,O121<=10%,V121="Completed"),"Platinum",IF(AND(P121>=50000,P121<100000,Q121>=3,V121="Completed"),"Gold",IF(AND(P121<50000,V121="Completed"),"Silver","Blacklisted")))) -> Blacklisted
A122: ORD10121 | B122: C003 | C122: P203 | D122: 14/12/2025 | E122: 16/12/2025 | F122: Rohit Singh | G122: Male | H122: 11/11/1993 | I122: Pune | J122: West | K122: Home Appliances | L122: Microwave | M122: 8 | N122: 8500 | O122: 20 | P122: 54400 | Q122: 3 | R122: Card | S122: Rahul | T122: rohit.singh@company.com | U122: 9208625306 | V122: Completed | W122: =IF(OR(Q122<=2,V122="Cancelled"),"Blacklisted",IF(AND(P122>=100000,Q122>=4,O122<=10%,V122="Completed"),"Platinum",IF(AND(P122>=50000,P122<100000,Q122>=3,V122="Completed"),"Gold",IF(AND(P122<50000,V122="Completed"),"Silver","Blacklisted")))) -> Gold
A123: ORD10122 | B123: C007 | C123: P303 | D123: 31/01/2026 | E123: 10/02/2026 | F123: Arjun Rao | G123: Male | H123: 01/02/2000 | I123: Bengaluru | J123: South | K123: Stationery | L123: Marker | M123: 3 | N123: 45 | O123: 0 | P123: 135 | Q123: 4 | R123: UPI | S123: Aisha | T123: arjun.rao@company.com | U123: 9970178536 | V123: Cancelled | W123: =IF(OR(Q123<=2,V123="Cancelled"),"Blacklisted",IF(AND(P123>=100000,Q123>=4,O123<=10%,V123="Completed"),"Platinum",IF(AND(P123>=50000,P123<100000,Q123>=3,V123="Completed"),"Gold",IF(AND(P123<50000,V123="Completed"),"Silver","Blacklisted")))) -> Blacklisted
A124: ORD10123 | B124: C001 | C124: P102 | D124: 03/01/2026 | E124: 04/01/2026 | F124: Amit Sharma | G124: Male | H124: 22/06/1986 | I124: Jaipur | J124: North | K124: Electronics | L124: Mouse | M124: 13 | N124: 700 | O124: 5 | P124: 8645 | Q124: 3 | R124: Card | S124: Neha | T124: amit.sharma@company.com | U124: 9633745195 | V124: Pending | W124: =IF(OR(Q124<=2,V124="Cancelled"),"Blacklisted",IF(AND(P124>=100000,Q124>=4,O124<=10%,V124="Completed"),"Platinum",IF(AND(P124>=50000,P124<100000,Q124>=3,V124="Completed"),"Gold",IF(AND(P124<50000,V124="Completed"),"Silver","Blacklisted")))) -> Blacklisted
A125: ORD10124 | B125: C004 | C125: P103 | D125: 20/10/2025 | E125: 26/10/2025 | F125: Anita Gupta | G125: Female | H125: 16/02/1986 | I125: Mumbai | J125: West | K125: Electronics | L125: Keyboard | M125: 14 | N125: 1200 | O125: 20 | P125: 13440 | Q125: 5 | R125: NetBanking | S125: Aisha | T125: anita.gupta@company.com | U125: 9922102053 | V125: Completed | W125: =IF(OR(Q125<=2,V125="Cancelled"),"Blacklisted",IF(AND(P125>=100000,Q125>=4,O125<=10%,V125="Completed"),"Platinum",IF(AND(P125>=50000,P125<100000,Q125>=3,V125="Completed"),"Gold",IF(AND(P125<50000,V125="Completed"),"Silver","Blacklisted")))) -> Silver
A126: ORD10125 | B126: C002 | C126: P303 | D126: 11/05/2025 | E126: 21/05/2025 | F126: Priya Patel | G126: Female | H126: 18/09/1991 | I126: Delhi | J126: North | K126: Stationery | L126: Marker | M126: 2 | N126: 45 | O126: 5 | P126: 85.5 | Q126: 3 | R126: UPI | S126: Ritika | T126: priya.patel@company.com | U126: 9135963930 | V126: Cancelled | W126: =IF(OR(Q126<=2,V126="Cancelled"),"Blacklisted",IF(AND(P126>=100000,Q126>=4,O126<=10%,V126="Completed"),"Platinum",IF(AND(P126>=50000,P126<100000,Q126>=3,V126="Completed"),"Gold",IF(AND(P126<50000,V126="Completed"),"Silver","Blacklisted")))) -> Blacklisted
A127: ORD10126 | B127: C004 | C127: P103 | D127: 02/01/2026 | E127: 06/01/2026 | F127: Anita Gupta | G127: Female | H127: 04/01/1981 | I127: Bengaluru | J127: South | K127: Electronics | L127: Keyboard | M127: 2 | N127: 1200 | O127: 20 | P127: 1920 | Q127: 3 | R127: Card | S127: Neha | T127: anita.gupta@company.com | U127: 9429405275 | V127: Completed | W127: =IF(OR(Q127<=2,V127="Cancelled"),"Blacklisted",IF(AND(P127>=100000,Q127>=4,O127<=10%,V127="Completed"),"Platinum",IF(AND(P127>=50000,P127<100000,Q127>=3,V127="Completed"),"Gold",IF(AND(P127<50000,V127="Completed"),"Silver","Blacklisted")))) -> Silver
A128: ORD10127 | B128: C003 | C128: P101 | D128: 20/04/2026 | E128: 26/04/2026 | F128: Rohit Singh | G128: Male | H128: 12/10/2004 | I128: Bengaluru | J128: South | K128: Electronics | L128: Laptop | M128: 10 | N128: 55000 | O128: 5 | P128: 522500 | Q128: 5 | R128: UPI | S128: Aisha | T128: rohit.singh@company.com | U128: 9521757571 | V128: Pending | W128: =IF(OR(Q128<=2,V128="Cancelled"),"Blacklisted",IF(AND(P128>=100000,Q128>=4,O128<=10%,V128="Completed"),"Platinum",IF(AND(P128>=50000,P128<100000,Q128>=3,V128="Completed"),"Gold",IF(AND(P128<50000,V128="Completed"),"Silver","Blacklisted")))) -> Blacklisted
A129: ORD10128 | B129: C006 | C129: P201 | D129: 04/08/2025 | E129: 05/08/2025 | F129: Sneha Joshi | G129: Female | H129: 25/03/1984 | I129: Jaipur | J129: North | K129: Home Appliances | L129: Mixer | M129: 15 | N129: 3500 | O129: 10 | P129: 47250 | Q129: 3 | R129: NetBanking | S129: Neha | T129: sneha.joshi@company.com | U129: 9467375455 | V129: Completed | W129: =IF(OR(Q129<=2,V129="Cancelled"),"Blacklisted",IF(AND(P129>=100000,Q129>=4,O129<=10%,V129="Completed"),"Platinum",IF(AND(P129>=50000,P129<100000,Q129>=3,V129="Completed"),"Gold",IF(AND(P129<50000,V129="Completed"),"Silver","Blacklisted")))) -> Silver
A130: ORD10129 | B130: C002 | C130: P202 | D130: 13/08/2025 | E130: 18/08/2025 | F130: Priya Patel | G130: Female | H130: 09/09/1982 | I130: Bengaluru | J130: South | K130: Home Appliances | L130: Iron | M130: 10 | N130: 2200 | O130: 15 | P130: 18700 | Q130: 4 | R130: Card | S130: Rahul | T130: priya.patel@company.com | U130: 9838809695 | V130: Pending | W130: =IF(OR(Q130<=2,V130="Cancelled"),"Blacklisted",IF(AND(P130>=100000,Q130>=4,O130<=10%,V130="Completed"),"Platinum",IF(AND(P130>=50000,P130<100000,Q130>=3,V130="Completed"),"Gold",IF(AND(P130<50000,V130="Completed"),"Silver","Blacklisted")))) -> Blacklisted
A131: ORD10130 | B131: C006 | C131: P201 | D131: 16/06/2025 | E131: 24/06/2025 | F131: Sneha Joshi | G131: Female | H131: 15/02/1993 | I131: Pune | J131: West | K131: Home Appliances | L131: Mixer | M131: 11 | N131: 3500 | O131: 5 | P131: 36575 | Q131: 5 | R131: Cash | S131: Ritika | T131: sneha.joshi@company.com | U131: 9296609782 | V131: Cancelled | W131: =IF(OR(Q131<=2,V131="Cancelled"),"Blacklisted",IF(AND(P131>=100000,Q131>=4,O131<=10%,V131="Completed"),"Platinum",IF(AND(P131>=50000,P131<100000,Q131>=3,V131="Completed"),"Gold",IF(AND(P131<50000,V131="Completed"),"Silver","Blacklisted")))) -> Blacklisted
A132: ORD10131 | B132: C004 | C132: P103 | D132: 27/04/2026 | E132: 30/04/2026 | F132: Anita Gupta | G132: Female | H132: 08/04/2003 | I132: Bengaluru | J132: South | K132: Electronics | L132: Keyboard | M132: 14 | N132: 1200 | O132: 0 | P132: 16800 | Q132: 5 | R132: Cash | S132: Rahul | T132: anita.gupta@company.com | U132: 9848259992 | V132: Cancelled | W132: =IF(OR(Q132<=2,V132="Cancelled"),"Blacklisted",IF(AND(P132>=100000,Q132>=4,O132<=10%,V132="Completed"),"Platinum",IF(AND(P132>=50000,P132<100000,Q132>=3,V132="Completed"),"Gold",IF(AND(P132<50000,V132="Completed"),"Silver","Blacklisted")))) -> Blacklisted
... A299: ORD10298 | B299: C003 | C299: P101 | D299: 13/01/2025 | E299: 16/01/2025 | F299: Rohit Singh | G299: Male | H299: 03/01/2004 | I299: Hyderabad | J299: South | K299: Electronics | L299: Laptop | M299: 11 | N299: 55000 | O299: 5 | P299: 574750 | Q299: 1 | R299: UPI | S299: Ritika | T299: rohit.singh@company.com | U299: 9482699727 | V299: Cancelled | W299: =IF(OR(Q299<=2,V299="Cancelled"),"Blacklisted",IF(AND(P299>=100000,Q299>=4,O299<=10%,V299="Completed"),"Platinum",IF(AND(P299>=50000,P299<100000,Q299>=3,V299="Completed"),"Gold",IF(AND(P299<50000,V299="Completed"),"Silver","Blacklisted")))) -> Blacklisted
A300: ORD10299 | B300: C007 | C300: P201 | D300: 05/10/2025 | E300: 17/10/2025 | F300: Arjun Rao | G300: Male | H300: 02/05/1992 | I300: Jaipur | J300: North | K300: Home Appliances | L300: Mixer | M300: 12 | N300: 3500 | O300: 0 | P300: 42000 | Q300: 2 | R300: NetBanking | T300: arjun.rao@company.com | U300: 9332473934 | V300: Pending | W300: =IF(OR(Q300<=2,V300="Cancelled"),"Blacklisted",IF(AND(P300>=100000,Q300>=4,O300<=10%,V300="Completed"),"Platinum",IF(AND(P300>=50000,P300<100000,Q300>=3,V300="Completed"),"Gold",IF(AND(P300<50000,V300="Completed"),"Silver","Blacklisted")))) -> Blacklisted
A301: ORD10300 | B301: C009 | C301: P303 | D301: 25/02/2026 | E301: 08/03/2026 | F301: Mohit Verma | G301: Male | H301: 26/01/2003 | I301: Hyderabad | J301: South | K301: Stationery | L301: Marker | M301: 15 | N301: 45 | O301: 10 | P301: 607.5 | Q301: 2 | R301: Cash | S301: Karan | T301: mohit.verma@company.com | U301: 9647657382 | V301: Pending | W301: =IF(OR(Q301<=2,V301="Cancelled"),"Blacklisted",IF(AND(P301>=100000,Q301>=4,O301<=10%,V301="Completed"),"Platinum",IF(AND(P301>=50000,P301<100000,Q301>=3,V301="Completed"),"Gold",IF(AND(P301<50000,V301="Completed"),"Silver","Blacklisted")))) -> Blacklisted
A302: ORD10301 | B302: C001 | C302: P303 | D302: 16/05/2025 | E302: 26/05/2025 | F302: Amit Sharma | G302: Male | H302: 20/05/1987 | I302: Bengaluru | J302: South | K302: Stationery | L302: Marker | M302: 13 | N302: 45 | O302: 0 | P302: 585 | Q302: 5 | R302: NetBanking | S302: Rahul | T302: amit.sharma@company.com | U302: 9736797776 | V302: Pending | W302: =IF(OR(Q302<=2,V302="Cancelled"),"Blacklisted",IF(AND(P302>=100000,Q302>=4,O302<=10%,V302="Completed"),"Platinum",IF(AND(P302>=50000,P302<100000,Q302>=3,V302="Completed"),"Gold",IF(AND(P302<50000,V302="Completed"),"Silver","Blacklisted")))) -> Blacklisted
A303: ORD10302 | B303: C003 | C303: P101 | D303: 02/01/2026 | E303: 05/01/2026 | F303: Rohit Singh | G303: Male | H303: 07/09/1975 | I303: Bengaluru | J303: South | K303: Electronics | L303: Laptop | M303: 8 | N303: 55000 | O303: 0 | P303: 440000 | Q303: 2 | R303: UPI | S303: Karan | T303: rohit.singh@company.com | U303: 9745773533 | V303: Cancelled | W303: =IF(OR(Q303<=2,V303="Cancelled"),"Blacklisted",IF(AND(P303>=100000,Q303>=4,O303<=10%,V303="Completed"),"Platinum",IF(AND(P303>=50000,P303<100000,Q303>=3,V303="Completed"),"Gold",IF(AND(P303<50000,V303="Completed"),"Silver","Blacklisted")))) -> Blacklisted
A304: ORD10303 | B304: C006 | C304: P101 | D304: 23/07/2025 | E304: 27/07/2025 | F304: Sneha Joshi | G304: Female | H304: 10/08/1980 | I304: Delhi | J304: North | K304: Electronics | L304: Laptop | M304: 4 | N304: 55000 | O304: 20 | P304: 176000 | Q304: 5 | R304: Cash | S304: Rahul | T304: sneha.joshi@company.com | U304: 9246715757 | V304: Pending | W304: =IF(OR(Q304<=2,V304="Cancelled"),"Blacklisted",IF(AND(P304>=100000,Q304>=4,O304<=10%,V304="Completed"),"Platinum",IF(AND(P304>=50000,P304<100000,Q304>=3,V304="Completed"),"Gold",IF(AND(P304<50000,V304="Completed"),"Silver","Blacklisted")))) -> Blacklisted
A305: ORD10304 | B305: C008 | C305: P201 | D305: 23/04/2026 | E305: 26/04/2026 | F305: Kavya Nair | G305: Female | H305: 07/04/1989 | I305: Ahmedabad | J305: West | K305: Home Appliances | L305: Mixer | M305: 19 | N305: 3500 | O305: 5 | P305: 63175 | Q305: 1 | R305: Card | S305: Neha | T305: kavya.nair@company.com | U305: 9904065774 | V305: Completed | W305: =IF(OR(Q305<=2,V305="Cancelled"),"Blacklisted",IF(AND(P305>=100000,Q305>=4,O305<=10%,V305="Completed"),"Platinum",IF(AND(P305>=50000,P305<100000,Q305>=3,V305="Completed"),"Gold",IF(AND(P305<50000,V305="Completed"),"Silver","Blacklisted")))) -> Blacklisted
A306: ORD10305 | B306: C005 | C306: P103 | D306: 02/03/2025 | E306: 06/03/2025 | F306: Vikas Mehta | G306: Male | H306: 20/08/1998 | I306: Jaipur | J306: North | K306: Electronics | L306: Keyboard | M306: 17 | N306: 1200 | O306: 15 | P306: 17340 | Q306: 2 | R306: NetBanking | S306: Rahul | T306: vikas.mehta@company.com | U306: 9652985385 | V306: Completed | W306: =IF(OR(Q306<=2,V306="Cancelled"),"Blacklisted",IF(AND(P306>=100000,Q306>=4,O306<=10%,V306="Completed"),"Platinum",IF(AND(P306>=50000,P306<100000,Q306>=3,V306="Completed"),"Gold",IF(AND(P306<50000,V306="Completed"),"Silver","Blacklisted")))) -> Blacklisted
A307: ORD10306 | B307: C008 | C307: P202 | D307: 09/02/2026 | E307: 17/02/2026 | F307: Kavya Nair | G307: Female | H307: 03/04/2001 | I307: Hyderabad | J307: South | K307: Home Appliances | L307: Iron | M307: 8 | N307: 2200 | O307: 5 | P307: 16720 | Q307: 3 | R307: Card | S307: Neha | T307: kavya.nair@company.com | U307: 9427001508 | V307: Pending | W307: =IF(OR(Q307<=2,V307="Cancelled"),"Blacklisted",IF(AND(P307>=100000,Q307>=4,O307<=10%,V307="Completed"),"Platinum",IF(AND(P307>=50000,P307<100000,Q307>=3,V307="Completed"),"Gold",IF(AND(P307<50000,V307="Completed"),"Silver","Blacklisted")))) -> Blacklisted
A308: ORD10307 | B308: C006 | C308: P102 | D308: 16/02/2025 | E308: 26/02/2025 | F308: Sneha Joshi | G308: Female | H308: 05/03/1992 | I308: Mumbai | J308: West | K308: Electronics | L308: Mouse | M308: 17 | N308: 700 | O308: 20 | P308: 9520 | Q308: 4 | R308: NetBanking | S308: Neha | T308: sneha.joshi@company.com | U308: 9666803655 | V308: Completed | W308: =IF(OR(Q308<=2,V308="Cancelled"),"Blacklisted",IF(AND(P308>=100000,Q308>=4,O308<=10%,V308="Completed"),"Platinum",IF(AND(P308>=50000,P308<100000,Q308>=3,V308="Completed"),"Gold",IF(AND(P308<50000,V308="Completed"),"Silver","Blacklisted")))) -> Silver
A309: ORD10308 | B309: C006 | C309: P203 | D309: 28/08/2025 | E309: 08/09/2025 | F309: Sneha Joshi | G309: Female | H309: 28/12/1976 | I309: Pune | J309: West | K309: Home Appliances | L309: Microwave | M309: 6 | N309: 8500 | O309: 15 | P309: 43350 | Q309: 1 | R309: Cash | S309: Aisha | T309: sneha.joshi@company.com | U309: 9134878547 | V309: Completed | W309: =IF(OR(Q309<=2,V309="Cancelled"),"Blacklisted",IF(AND(P309>=100000,Q309>=4,O309<=10%,V309="Completed"),"Platinum",IF(AND(P309>=50000,P309<100000,Q309>=3,V309="Completed"),"Gold",IF(AND(P309<50000,V309="Completed"),"Silver","Blacklisted")))) -> Blacklisted
A310: ORD10309 | B310: C010 | C310: P201 | D310: 06/10/2025 | E310: 11/10/2025 | F310: Pooja Shah | G310: Female | H310: 04/09/1986 | I310: Hyderabad | J310: South | K310: Home Appliances | L310: Mixer | M310: 3 | N310: 3500 | O310: 10 | P310: 9450 | Q310: 1 | R310: NetBanking | S310: Rahul | T310: pooja.shah@company.com | U310: 9253593557 | V310: Completed | W310: =IF(OR(Q310<=2,V310="Cancelled"),"Blacklisted",IF(AND(P310>=100000,Q310>=4,O310<=10%,V310="Completed"),"Platinum",IF(AND(P310>=50000,P310<100000,Q310>=3,V310="Completed"),"Gold",IF(AND(P310<50000,V310="Completed"),"Silver","Blacklisted")))) -> Blacklisted
A311: ORD10310 | B311: C009 | C311: P104 | D311: 17/01/2025 | E311: 29/01/2025 | F311: Mohit Verma | G311: Male | H311: 14/08/1989 | I311: Ahmedabad | J311: West | K311: Electronics | L311: Monitor | M311: 2 | N311: 12000 | O311: 20 | P311: 19200 | Q311: 1 | R311: Card | S311: Aisha | T311: mohit.verma@company.com | U311: 9183094051 | V311: Completed | W311: =IF(OR(Q311<=2,V311="Cancelled"),"Blacklisted",IF(AND(P311>=100000,Q311>=4,O311<=10%,V311="Completed"),"Platinum",IF(AND(P311>=50000,P311<100000,Q311>=3,V311="Completed"),"Gold",IF(AND(P311<50000,V311="Completed"),"Silver","Blacklisted")))) -> Blacklisted
A312: ORD10311 | B312: C005 | C312: P302 | D312: 13/10/2025 | E312: 16/10/2025 | F312: Vikas Mehta | G312: Male | H312: 02/03/1991 | I312: Delhi | J312: North | K312: Stationery | L312: Pen | M312: 12 | N312: 20 | O312: 20 | P312: 192 | Q312: 2 | R312: Card | S312: Rahul | T312: vikas.mehta@company.com | U312: 9293147620 | V312: Completed | W312: =IF(OR(Q312<=2,V312="Cancelled"),"Blacklisted",IF(AND(P312>=100000,Q312>=4,O312<=10%,V312="Completed"),"Platinum",IF(AND(P312>=50000,P312<100000,Q312>=3,V312="Completed"),"Gold",IF(AND(P312<50000,V312="Completed"),"Silver","Blacklisted")))) -> Blacklisted
... A370: ORD10369 | B370: C010 | C370: P301 | D370: 01/04/2026 | E370: 05/04/2026 | F370: Pooja Shah | G370: Female | H370: 04/01/1987 | I370: Hyderabad | J370: South | K370: Stationery | L370: Notebook | M370: 19 | N370: 60 | O370: 15 | P370: 969 | Q370: 4 | R370: NetBanking | S370: Neha | T370: pooja.shah@company.com | U370: 9435947486 | V370: Cancelled | W370: =IF(OR(Q370<=2,V370="Cancelled"),"Blacklisted",IF(AND(P370>=100000,Q370>=4,O370<=10%,V370="Completed"),"Platinum",IF(AND(P370>=50000,P370<100000,Q370>=3,V370="Completed"),"Gold",IF(AND(P370<50000,V370="Completed"),"Silver","Blacklisted")))) -> Blacklisted
A371: ORD10370 | B371: C001 | C371: P101 | E371: 02/02/2025 | F371: Amit Sharma | G371: Male | H371: 14/05/1992 | I371: Delhi | J371: North | K371: Electronics | L371: Laptop | M371: 15 | N371: 55000 | O371: 0 | P371: 825000 | Q371: 5 | R371: Card | S371: Neha | T371: amit.sharma@company.com | U371: 9411668831 | V371: Cancelled | W371: =IF(OR(Q371<=2,V371="Cancelled"),"Blacklisted",IF(AND(P371>=100000,Q371>=4,O371<=10%,V371="Completed"),"Platinum",IF(AND(P371>=50000,P371<100000,Q371>=3,V371="Completed"),"Gold",IF(AND(P371<50000,V371="Completed"),"Silver","Blacklisted")))) -> Blacklisted
A372: ORD10371 | B372: C009 | C372: P303 | D372: 06/10/2025 | E372: 08/10/2025 | F372: Mohit Verma | G372: Male | H372: 03/05/1989 | I372: Bengaluru | J372: South | K372: Stationery | L372: Marker | M372: 11 | N372: 45 | O372: 5 | P372: 470.25 | Q372: 5 | R372: NetBanking | S372: Karan | T372: mohit.verma@company.com | U372: 9523682403 | V372: Completed | W372: =IF(OR(Q372<=2,V372="Cancelled"),"Blacklisted",IF(AND(P372>=100000,Q372>=4,O372<=10%,V372="Completed"),"Platinum",IF(AND(P372>=50000,P372<100000,Q372>=3,V372="Completed"),"Gold",IF(AND(P372<50000,V372="Completed"),"Silver","Blacklisted")))) -> Silver
A373: ORD10372 | B373: C006 | C373: P302 | D373: 12/06/2025 | E373: 17/06/2025 | F373: Sneha Joshi | G373: Female | H373: 19/12/1990 | I373: Jaipur | J373: North | K373: Stationery | L373: Pen | M373: 9 | N373: 20 | O373: 10 | P373: 162 | Q373: 1 | R373: Card | S373: Rahul | T373: sneha.joshi@company.com | U373: 9652936744 | V373: Cancelled | W373: =IF(OR(Q373<=2,V373="Cancelled"),"Blacklisted",IF(AND(P373>=100000,Q373>=4,O373<=10%,V373="Completed"),"Platinum",IF(AND(P373>=50000,P373<100000,Q373>=3,V373="Completed"),"Gold",IF(AND(P373<50000,V373="Completed"),"Silver","Blacklisted")))) -> Blacklisted
A374: ORD10373 | B374: C004 | C374: P303 | D374: 18/11/2025 | E374: 20/11/2025 | F374: Anita Gupta | G374: Female | H374: 09/07/1995 | I374: Bengaluru | J374: South | K374: Stationery | L374: Marker | M374: 5 | N374: 45 | O374: 5 | P374: 213.75 | Q374: 3 | R374: Card | S374: Neha | T374: anita.gupta@company.com | U374: 9726464733 | V374: Pending | W374: =IF(OR(Q374<=2,V374="Cancelled"),"Blacklisted",IF(AND(P374>=100000,Q374>=4,O374<=10%,V374="Completed"),"Platinum",IF(AND(P374>=50000,P374<100000,Q374>=3,V374="Completed"),"Gold",IF(AND(P374<50000,V374="Completed"),"Silver","Blacklisted")))) -> Blacklisted
A375: ORD10374 | B375: C007 | C375: P102 | D375: 01/11/2025 | E375: 02/11/2025 | F375: Arjun Rao | G375: Male | H375: 23/12/1998 | I375: Hyderabad | J375: South | K375: Electronics | L375: Mouse | M375: 5 | N375: 700 | O375: 10 | P375: 3150 | Q375: 2 | R375: UPI | S375: Rahul | T375: arjun.rao@company.com | U375: 9273520544 | V375: Completed | W375: =IF(OR(Q375<=2,V375="Cancelled"),"Blacklisted",IF(AND(P375>=100000,Q375>=4,O375<=10%,V375="Completed"),"Platinum",IF(AND(P375>=50000,P375<100000,Q375>=3,V375="Completed"),"Gold",IF(AND(P375<50000,V375="Completed"),"Silver","Blacklisted")))) -> Blacklisted
A376: ORD10375 | B376: C005 | C376: P102 | D376: 24/01/2025 | E376: 31/01/2025 | F376: Vikas Mehta | G376: Male | H376: 23/12/1979 | I376: Kolkata | J376: East | K376: Electronics | L376: Mouse | M376: 1 | N376: 700 | O376: 0 | P376: 700 | Q376: 1 | R376: UPI | S376: Karan | T376: vikas.mehta@company.com | U376: 9374259988 | V376: Completed | W376: =IF(OR(Q376<=2,V376="Cancelled"),"Blacklisted",IF(AND(P376>=100000,Q376>=4,O376<=10%,V376="Completed"),"Platinum",IF(AND(P376>=50000,P376<100000,Q376>=3,V376="Completed"),"Gold",IF(AND(P376<50000,V376="Completed"),"Silver","Blacklisted")))) -> Blacklisted
A377: ORD10376 | B377: C008 | C377: P102 | D377: 13/02/2026 | E377: 21/02/2026 | F377: Kavya Nair | G377: Female | H377: 15/12/1975 | I377: Mumbai | J377: West | K377: Electronics | L377: Mouse | M377: 13 | N377: 700 | O377: 20 | P377: 7280 | Q377: 2 | R377: Card | S377: Ritika | T377: kavya.nair@company.com | U377: 9538129419 | V377: Completed | W377: =IF(OR(Q377<=2,V377="Cancelled"),"Blacklisted",IF(AND(P377>=100000,Q377>=4,O377<=10%,V377="Completed"),"Platinum",IF(AND(P377>=50000,P377<100000,Q377>=3,V377="Completed"),"Gold",IF(AND(P377<50000,V377="Completed"),"Silver","Blacklisted")))) -> Blacklisted
A378: ORD10377 | B378: C009 | C378: P104 | D378: 08/02/2025 | E378: 19/02/2025 | F378: Mohit Verma | G378: Male | H378: 17/05/1993 | I378: Pune | J378: West | K378: Electronics | L378: Monitor | M378: 20 | N378: 12000 | O378: 0 | P378: 240000 | Q378: 2 | R378: Card | S378: Neha | T378: mohit.verma@company.com | U378: 9382815686 | V378: Completed | W378: =IF(OR(Q378<=2,V378="Cancelled"),"Blacklisted",IF(AND(P378>=100000,Q378>=4,O378<=10%,V378="Completed"),"Platinum",IF(AND(P378>=50000,P378<100000,Q378>=3,V378="Completed"),"Gold",IF(AND(P378<50000,V378="Completed"),"Silver","Blacklisted")))) -> Blacklisted
A379: ORD10378 | B379: C007 | C379: P103 | D379: 28/12/2025 | E379: 06/01/2026 | F379: Arjun Rao | G379: Male | H379: 17/09/1976 | I379: Kolkata | J379: East | K379: Electronics | L379: Keyboard | M379: 9 | N379: 1200 | O379: 15 | P379: 9180 | Q379: 1 | R379: UPI | S379: Ritika | T379: arjun.rao@company.com | U379: 9450746157 | V379: Pending | W379: =IF(OR(Q379<=2,V379="Cancelled"),"Blacklisted",IF(AND(P379>=100000,Q379>=4,O379<=10%,V379="Completed"),"Platinum",IF(AND(P379>=50000,P379<100000,Q379>=3,V379="Completed"),"Gold",IF(AND(P379<50000,V379="Completed"),"Silver","Blacklisted")))) -> Blacklisted
A380: ORD10379 | B380: C007 | C380: P302 | D380: 01/10/2025 | E380: 03/10/2025 | F380: Arjun Rao | G380: Male | H380: 22/12/1996 | I380: Jaipur | J380: North | K380: Stationery | L380: Pen | M380: 3 | N380: 20 | O380: 15 | P380: 51 | Q380: 3 | R380: Cash | S380: Neha | T380: arjun.rao@company.com | U380: 9349012570 | V380: Pending | W380: =IF(OR(Q380<=2,V380="Cancelled"),"Blacklisted",IF(AND(P380>=100000,Q380>=4,O380<=10%,V380="Completed"),"Platinum",IF(AND(P380>=50000,P380<100000,Q380>=3,V380="Completed"),"Gold",IF(AND(P380<50000,V380="Completed"),"Silver","Blacklisted")))) -> Blacklisted
A381: ORD10380 | B381: C006 | C381: P101 | D381: 18/12/2025 | E381: 19/12/2025 | F381: Sneha Joshi | G381: Female | H381: 25/12/1995 | I381: Delhi | J381: North | K381: Electronics | L381: Laptop | M381: 8 | N381: 55000 | O381: 20 | P381: 352000 | Q381: 5 | R381: Card | S381: Karan | T381: sneha.joshi@company.com | U381: 9442163790 | V381: Pending | W381: =IF(OR(Q381<=2,V381="Cancelled"),"Blacklisted",IF(AND(P381>=100000,Q381>=4,O381<=10%,V381="Completed"),"Platinum",IF(AND(P381>=50000,P381<100000,Q381>=3,V381="Completed"),"Gold",IF(AND(P381<50000,V381="Completed"),"Silver","Blacklisted")))) -> Blacklisted
A382: ORD10381 | B382: C006 | C382: P301 | D382: 29/09/2025 | E382: 07/10/2025 | F382: Sneha Joshi | G382: Female | H382: 23/06/1985 | I382: Delhi | J382: North | K382: Stationery | L382: Notebook | M382: 17 | N382: 60 | O382: 20 | P382: 816 | Q382: 1 | R382: UPI | S382: Ritika | T382: sneha.joshi@company.com | U382: 9953329223 | V382: Pending | W382: =IF(OR(Q382<=2,V382="Cancelled"),"Blacklisted",IF(AND(P382>=100000,Q382>=4,O382<=10%,V382="Completed"),"Platinum",IF(AND(P382>=50000,P382<100000,Q382>=3,V382="Completed"),"Gold",IF(AND(P382<50000,V382="Completed"),"Silver","Blacklisted")))) -> Blacklisted
A383: ORD10382 | B383: C003 | C383: P302 | D383: 14/05/2025 | E383: 22/05/2025 | F383: Rohit Singh | G383: Male | H383: 10/02/1984 | I383: Bengaluru | J383: South | K383: Stationery | L383: Pen | M383: 4 | N383: 20 | O383: 15 | P383: 68 | Q383: 3 | R383: NetBanking | S383: Aisha | T383: rohit.singh@company.com | U383: 9202321359 | V383: Pending | W383: =IF(OR(Q383<=2,V383="Cancelled"),"Blacklisted",IF(AND(P383>=100000,Q383>=4,O383<=10%,V383="Completed"),"Platinum",IF(AND(P383>=50000,P383<100000,Q383>=3,V383="Completed"),"Gold",IF(AND(P383<50000,V383="Completed"),"Silver","Blacklisted")))) -> Blacklisted
... A399: ORD10398 | B399: C007 | C399: P104 | D399: 31/01/2025 | E399: 04/02/2025 | F399: Arjun Rao | G399: Male | H399: 10/12/1978 | I399: Kolkata | J399: East | K399: Electronics | L399: Monitor | M399: 19 | N399: 12000 | O399: 0 | P399: 228000 | Q399: 4 | R399: UPI | S399: Aisha | T399: arjun.rao@company.com | U399: 9136906750 | V399: Pending | W399: =IF(OR(Q399<=2,V399="Cancelled"),"Blacklisted",IF(AND(P399>=100000,Q399>=4,O399<=10%,V399="Completed"),"Platinum",IF(AND(P399>=50000,P399<100000,Q399>=3,V399="Completed"),"Gold",IF(AND(P399<50000,V399="Completed"),"Silver","Blacklisted")))) -> Blacklisted
A400: ORD10399 | B400: C001 | C400: P102 | E400: 03/11/2025 | F400: Amit Sharma | G400: Male | H400: 01/09/1979 | I400: Bengaluru | J400: South | K400: Electronics | L400: Mouse | M400: 12 | N400: 700 | O400: 15 | P400: 7140 | Q400: 3 | R400: Card | S400: Ritika | T400: amit.sharma@company.com | U400: 9485286324 | V400: Completed | W400: =IF(OR(Q400<=2,V400="Cancelled"),"Blacklisted",IF(AND(P400>=100000,Q400>=4,O400<=10%,V400="Completed"),"Platinum",IF(AND(P400>=50000,P400<100000,Q400>=3,V400="Completed"),"Gold",IF(AND(P400<50000,V400="Completed"),"Silver","Blacklisted")))) -> Silver
A401: ORD10400 | B401: C008 | C401: P103 | D401: 13/05/2025 | E401: 21/05/2025 | F401: Kavya Nair | G401: Female | H401: 08/04/2001 | I401: Delhi | J401: North | K401: Electronics | L401: Keyboard | M401: 16 | N401: 1200 | O401: 20 | P401: 15360 | Q401: 1 | R401: Cash | S401: Rahul | T401: kavya.nair@company.com | U401: 9414633966 | V401: Pending | W401: =IF(OR(Q401<=2,V401="Cancelled"),"Blacklisted",IF(AND(P401>=100000,Q401>=4,O401<=10%,V401="Completed"),"Platinum",IF(AND(P401>=50000,P401<100000,Q401>=3,V401="Completed"),"Gold",IF(AND(P401<50000,V401="Completed"),"Silver","Blacklisted")))) -> Blacklisted
A402: ORD10401 | B402: C009 | C402: P203 | D402: 27/12/2025 | E402: 04/01/2026 | F402: Mohit Verma | G402: Male | H402: 01/01/1983 | I402: Hyderabad | J402: South | K402: Home Appliances | L402: Microwave | M402: 10 | N402: 8500 | O402: 5 | P402: 80750 | Q402: 5 | R402: NetBanking | S402: Ritika | T402: mohit.verma@company.com | U402: 9833735234 | V402: Completed | W402: =IF(OR(Q402<=2,V402="Cancelled"),"Blacklisted",IF(AND(P402>=100000,Q402>=4,O402<=10%,V402="Completed"),"Platinum",IF(AND(P402>=50000,P402<100000,Q402>=3,V402="Completed"),"Gold",IF(AND(P402<50000,V402="Completed"),"Silver","Blacklisted")))) -> Gold
A403: ORD10402 | B403: C008 | C403: P302 | D403: 11/02/2025 | E403: 21/02/2025 | F403: Kavya Nair | G403: Female | H403: 09/08/1989 | I403: Ahmedabad | J403: West | K403: Stationery | L403: Pen | M403: 18 | N403: 20 | O403: 20 | P403: 288 | Q403: 1 | R403: UPI | S403: Ritika | T403: kavya.nair@company.com | U403: 9523689108 | V403: Pending | W403: =IF(OR(Q403<=2,V403="Cancelled"),"Blacklisted",IF(AND(P403>=100000,Q403>=4,O403<=10%,V403="Completed"),"Platinum",IF(AND(P403>=50000,P403<100000,Q403>=3,V403="Completed"),"Gold",IF(AND(P403<50000,V403="Completed"),"Silver","Blacklisted")))) -> Blacklisted
A404: ORD10403 | B404: C009 | C404: P203 | D404: 13/03/2026 | E404: 19/03/2026 | F404: Mohit Verma | G404: Male | H404: 22/10/1993 | I404: Mumbai | J404: West | K404: Home Appliances | L404: Microwave | M404: 9 | N404: 8500 | O404: 0 | P404: 76500 | Q404: 2 | R404: Card | S404: Ritika | T404: mohit.verma@company.com | U404: 9812909831 | V404: Pending | W404: =IF(OR(Q404<=2,V404="Cancelled"),"Blacklisted",IF(AND(P404>=100000,Q404>=4,O404<=10%,V404="Completed"),"Platinum",IF(AND(P404>=50000,P404<100000,Q404>=3,V404="Completed"),"Gold",IF(AND(P404<50000,V404="Completed"),"Silver","Blacklisted")))) -> Blacklisted
A405: ORD10404 | B405: C008 | C405: P203 | D405: 01/10/2025 | E405: 12/10/2025 | F405: Kavya Nair | G405: Female | H405: 05/05/2000 | I405: Mumbai | J405: West | K405: Home Appliances | L405: Microwave | M405: 8 | N405: 8500 | O405: 10 | P405: 61200 | Q405: 4 | R405: Cash | S405: Neha | T405: kavya.nair@company.com | U405: 9106290987 | V405: Cancelled | W405: =IF(OR(Q405<=2,V405="Cancelled"),"Blacklisted",IF(AND(P405>=100000,Q405>=4,O405<=10%,V405="Completed"),"Platinum",IF(AND(P405>=50000,P405<100000,Q405>=3,V405="Completed"),"Gold",IF(AND(P405<50000,V405="Completed"),"Silver","Blacklisted")))) -> Blacklisted
...

Sheet Product_master
A1: Product_ID | B1: Product_Name | C1: Category | D1: Supplier | E1: Cost_Price | F1: Warranty_Months
A2: P101 | B2: Laptop | C2: Electronics | D2: TechHub | E2: 41250 | F2: 12
A3: P102 | B3: Mouse | C3: Electronics | D3: TechHub | E3: 525 | F3: 24
A4: P103 | B4: Keyboard | C4: Electronics | D4: TechHub | E4: 900 | F4: 6
A5: P104 | B5: Monitor | C5: Electronics | D5: Global Trade | E5: 9000 | F5: 24
A6: P201 | B6: Mixer | C6: Home Appliances | D6: Global Trade | E6: 2625 | F6: 6
A7: P202 | B7: Iron | C7: Home Appliances | D7: Global Trade | E7: 1650 | F7: 24
A8: P203 | B8: Microwave | C8: Home Appliances | D8: TechHub | E8: 6375 | F8: 24
A9: P301 | B9: Notebook | C9: Stationery | D9: ABC Corp | E9: 45 | F9: 12
A10: P302 | B10: Pen | C10: Stationery | D10: Prime Supplies | E10: 15 | F10: 12
A11: P303 | B11: Marker | C11: Stationery | D11: TechHub | E11: 33.75 | F11: 12

Sheet Customer_master
A1: Customer_ID | B1: Customer_Name | C1: Membership | D1: State
A2: C001 | B2: Amit Sharma | C2: Silver | D2: RJ
A3: C002 | B3: Priya Patel | C3: Platinum | D3: WB
A4: C003 | B4: Rohit Singh | C4: Gold | D4: DL
A5: C004 | B5: Anita Gupta | C5: Gold | D5: WB
A6: C005 | B6: Vikas Mehta | C6: Gold | D6: DL
A7: C006 | B7: Sneha Joshi | C7: Gold | D7: WB
A8: C007 | B8: Arjun Rao | C8: Silver | D8: RJ
A9: C008 | B9: Kavya Nair | C9: Silver | D9: WB
A10: C009 | B10: Mohit Verma | C10: Platinum | D10: KA
A11: C010 | B11: Pooja Shah | C11: Silver | D11: WB

Sheet Q2 Customer Standardization
A1: Q2 – Customer Data Standardization
A3: Customer ID | B3: Original Customer Name | C3: Standardized Customer Name | D3: Customer Code | E3: Standardized Email
A4: =Sales_data!B2 -> C008 | B4: =Sales_data!F2 -> Kavya Nair | C4: =PROPER(TRIM(Sales_data!F2)) -> Kavya Nair | D4: =LEFT(C4,3)&RIGHT(A4,3)&LEFT(Sales_data!I2,2) -> Kav008Hy | E4: =IF(ISNUMBER(SEARCH("@",Sales_data!T2)),LOWER(SUBSTITUTE(Sales_data!T2," ","")),"Invalid Email") -> kavya.nair@company.com
A5: =Sales_data!B3 -> C008 | B5: =Sales_data!F3 -> Kavya Nair | C5: =PROPER(TRIM(Sales_data!F3)) -> Kavya Nair | D5: =LEFT(C5,3)&RIGHT(A5,3)&LEFT(Sales_data!I3,2) -> Kav008De | E5: =IF(ISNUMBER(SEARCH("@",Sales_data!T3)),LOWER(SUBSTITUTE(Sales_data!T3," ","")),"Invalid Email") -> kavya.nair@company.com
A6: =Sales_data!B4 -> C010 | B6: =Sales_data!F4 -> pooja shah | C6: =PROPER(TRIM(Sales_data!F4)) -> Pooja Shah | D6: =LEFT(C6,3)&RIGHT(A6,3)&LEFT(Sales_data!I4,2) -> Poo010Be | E6: =IF(ISNUMBER(SEARCH("@",Sales_data!T4)),LOWER(SUBSTITUTE(Sales_data!T4," ","")),"Invalid Email") -> pooja.shah@company.com
A7: =Sales_data!B5 -> C008 | B7: =Sales_data!F5 -> Kavya Nair | C7: =PROPER(TRIM(Sales_data!F5)) -> Kavya Nair | D7: =LEFT(C7,3)&RIGHT(A7,3)&LEFT(Sales_data!I5,2) -> Kav008Be | E7: =IF(ISNUMBER(SEARCH("@",Sales_data!T5)),LOWER(SUBSTITUTE(Sales_data!T5," ","")),"Invalid Email") -> kavya.nair@company.com
A8: =Sales_data!B6 -> C009 | B8: =Sales_data!F6 -> Mohit Verma | C8: =PROPER(TRIM(Sales_data!F6)) -> Mohit Verma | D8: =LEFT(C8,3)&RIGHT(A8,3)&LEFT(Sales_data!I6,2) -> Moh009De | E8: =IF(ISNUMBER(SEARCH("@",Sales_data!T6)),LOWER(SUBSTITUTE(Sales_data!T6," ","")),"Invalid Email") -> mohit.verma@company.com
A9: =Sales_data!B7 -> C007 | B9: =Sales_data!F7 -> arjun Rao | C9: =PROPER(TRIM(Sales_data!F7)) -> Arjun Rao | D9: =LEFT(C9,3)&RIGHT(A9,3)&LEFT(Sales_data!I7,2) -> Arj007Hy | E9: =IF(ISNUMBER(SEARCH("@",Sales_data!T7)),LOWER(SUBSTITUTE(Sales_data!T7," ","")),"Invalid Email") -> arjun.rao@company.com
A10: =Sales_data!B8 -> C008 | B10: =Sales_data!F8 -> Kavya Nair | C10: =PROPER(TRIM(Sales_data!F8)) -> Kavya Nair | D10: =LEFT(C10,3)&RIGHT(A10,3)&LEFT(Sales_data!I8,2) -> Kav008Hy | E10: =IF(ISNUMBER(SEARCH("@",Sales_data!T8)),LOWER(SUBSTITUTE(Sales_data!T8," ","")),"Invalid Email") -> kavya.nair@company.com
A11: =Sales_data!B9 -> C002 | B11: =Sales_data!F9 -> Priya Patel | C11: =PROPER(TRIM(Sales_data!F9)) -> Priya Patel | D11: =LEFT(C11,3)&RIGHT(A11,3)&LEFT(Sales_data!I9,2) -> Pri002Mu | E11: =IF(ISNUMBER(SEARCH("@",Sales_data!T9)),LOWER(SUBSTITUTE(Sales_data!T9," ","")),"Invalid Email") -> priya.patel@company.com
A12: =Sales_data!B10 -> C008 | B12: =Sales_data!F10 -> kavya Nair | C12: =PROPER(TRIM(Sales_data!F10)) -> Kavya Nair | D12: =LEFT(C12,3)&RIGHT(A12,3)&LEFT(Sales_data!I10,2) -> Kav008Pu | E12: =IF(ISNUMBER(SEARCH("@",Sales_data!T10)),LOWER(SUBSTITUTE(Sales_data!T10," ","")),"Invalid Email") -> kavya.nair@company.com
A13: =Sales_data!B11 -> C002 | B13: =Sales_data!F11 -> Priya Patel | C13: =PROPER(TRIM(Sales_data!F11)) -> Priya Patel | D13: =LEFT(C13,3)&RIGHT(A13,3)&LEFT(Sales_data!I11,2) -> Pri002Mu | E13: =IF(ISNUMBER(SEARCH("@",Sales_data!T11)),LOWER(SUBSTITUTE(Sales_data!T11," ","")),"Invalid Email") -> priya.patel@company.com
A14: =Sales_data!B12 -> C003 | B14: =Sales_data!F12 -> Rohit Singh | C14: =PROPER(TRIM(Sales_data!F12)) -> Rohit Singh | D14: =LEFT(C14,3)&RIGHT(A14,3)&LEFT(Sales_data!I12,2) -> Roh003De | E14: =IF(ISNUMBER(SEARCH("@",Sales_data!T12)),LOWER(SUBSTITUTE(Sales_data!T12," ","")),"Invalid Email") -> rohit.singh@company.com
A15: =Sales_data!B13 -> C008 | B15: =Sales_data!F13 -> Kavya Nair | C15: =PROPER(TRIM(Sales_data!F13)) -> Kavya Nair | D15: =LEFT(C15,3)&RIGHT(A15,3)&LEFT(Sales_data!I13,2) -> Kav008Ah | E15: =IF(ISNUMBER(SEARCH("@",Sales_data!T13)),LOWER(SUBSTITUTE(Sales_data!T13," ","")),"Invalid Email") -> kavya.nair@company.com
... A503: =Sales_data!B501 -> C002 | B503: =Sales_data!F501 -> Priya Patel | C503: =PROPER(TRIM(Sales_data!F501)) -> Priya Patel | D503: =LEFT(C503,3)&RIGHT(A503,3)&LEFT(Sales_data!I501,2) -> Pri002Be | E503: =IF(ISNUMBER(SEARCH("@",Sales_data!T501)),LOWER(SUBSTITUTE(Sales_data!T501," ","")),"Invalid Email") -> priya.patel@company.com

Sheet Q3 Order Delivery Analysis
A1: Q3 – Order & Delivery Analysis
A3: Order ID | B3: DOB | C3: Customer Age | D3: Order Date | E3: Delivery Date | F3: Delivery Time (Days) | G3: Delivery Status
A4: =Sales_data!A2 -> ORD10001 | B4: =Sales_data!H2 -> 01/08/1976 | C4: =IFERROR(DATEDIF(DATE(VALUE(RIGHT(B4,4)),VALUE(MID(B4,4,2)),VALUE(LEFT(B4,2))),TODAY(),"Y"),"") -> 50 | D4: =Sales_data!D2 -> 18/09/2025 | E4: =Sales_data!E2 -> 22/09/2025 | F4: =IF(E4="","",IFERROR(DATE(VALUE(RIGHT(E4,4)),VALUE(MID(E4,4,2)),VALUE(LEFT(E4,2)))-DATE(VALUE(RIGHT(D4,4)),VALUE(MID(D4,4,2)),VALUE(LEFT(D4,2))),"")) -> 4 | G4: =IF(E4="","Pending",IF(F4="","Pending",IF(F4<=5,"OnTime","Delayed"))) -> OnTime
A5: =Sales_data!A3 -> ORD10002 | B5: =Sales_data!H3 -> 16/10/2000 | C5: =IFERROR(DATEDIF(DATE(VALUE(RIGHT(B5,4)),VALUE(MID(B5,4,2)),VALUE(LEFT(B5,2))),TODAY(),"Y"),"") -> 25 | D5: =Sales_data!D3 -> 27/04/2025 | E5: =Sales_data!E3 -> 04/05/2025 | F5: =IF(E5="","",IFERROR(DATE(VALUE(RIGHT(E5,4)),VALUE(MID(E5,4,2)),VALUE(LEFT(E5,2)))-DATE(VALUE(RIGHT(D5,4)),VALUE(MID(D5,4,2)),VALUE(LEFT(D5,2))),"")) -> 7 | G5: =IF(E5="","Pending",IF(F5="","Pending",IF(F5<=5,"OnTime","Delayed"))) -> Delayed
A6: =Sales_data!A4 -> ORD10003 | B6: =Sales_data!H4 -> 16/09/1994 | C6: =IFERROR(DATEDIF(DATE(VALUE(RIGHT(B6,4)),VALUE(MID(B6,4,2)),VALUE(LEFT(B6,2))),TODAY(),"Y"),"") -> 32 | D6: =Sales_data!D4 -> 03/09/2025 | E6: =Sales_data!E4 -> 14/09/2025 | F6: =IF(E6="","",IFERROR(DATE(VALUE(RIGHT(E6,4)),VALUE(MID(E6,4,2)),VALUE(LEFT(E6,2)))-DATE(VALUE(RIGHT(D6,4)),VALUE(MID(D6,4,2)),VALUE(LEFT(D6,2))),"")) -> 11 | G6: =IF(E6="","Pending",IF(F6="","Pending",IF(F6<=5,"OnTime","Delayed"))) -> Delayed
A7: =Sales_data!A5 -> ORD10002 | B7: =Sales_data!H5 -> 07/03/2004 | C7: =IFERROR(DATEDIF(DATE(VALUE(RIGHT(B7,4)),VALUE(MID(B7,4,2)),VALUE(LEFT(B7,2))),TODAY(),"Y"),"") -> 22 | D7: =Sales_data!D5 -> 21/03/2026 | E7: =Sales_data!E5 -> 02/04/2026 | F7: =IF(E7="","",IFERROR(DATE(VALUE(RIGHT(E7,4)),VALUE(MID(E7,4,2)),VALUE(LEFT(E7,2)))-DATE(VALUE(RIGHT(D7,4)),VALUE(MID(D7,4,2)),VALUE(LEFT(D7,2))),"")) -> 12 | G7: =IF(E7="","Pending",IF(F7="","Pending",IF(F7<=5,"OnTime","Delayed"))) -> Delayed
A8: =Sales_data!A6 -> ORD10005 | B8: =Sales_data!H6 -> 13/04/1976 | C8: =IFERROR(DATEDIF(DATE(VALUE(RIGHT(B8,4)),VALUE(MID(B8,4,2)),VALUE(LEFT(B8,2))),TODAY(),"Y"),"") -> 50 | D8: =Sales_data!D6 -> 27/09/2025 | E8: =Sales_data!E6 -> 07/10/2025 | F8: =IF(E8="","",IFERROR(DATE(VALUE(RIGHT(E8,4)),VALUE(MID(E8,4,2)),VALUE(LEFT(E8,2)))-DATE(VALUE(RIGHT(D8,4)),VALUE(MID(D8,4,2)),VALUE(LEFT(D8,2))),"")) -> 10 | G8: =IF(E8="","Pending",IF(F8="","Pending",IF(F8<=5,"OnTime","Delayed"))) -> Delayed
A9: =Sales_data!A7 -> ORD10006 | B9: =Sales_data!H7 -> 07/02/1988 | C9: =IFERROR(DATEDIF(DATE(VALUE(RIGHT(B9,4)),VALUE(MID(B9,4,2)),VALUE(LEFT(B9,2))),TODAY(),"Y"),"") -> 38 | D9: =Sales_data!D7 -> 04/01/2026 | E9: =Sales_data!E7 -> 12/01/2026 | F9: =IF(E9="","",IFERROR(DATE(VALUE(RIGHT(E9,4)),VALUE(MID(E9,4,2)),VALUE(LEFT(E9,2)))-DATE(VALUE(RIGHT(D9,4)),VALUE(MID(D9,4,2)),VALUE(LEFT(D9,2))),"")) -> 8 | G9: =IF(E9="","Pending",IF(F9="","Pending",IF(F9<=5,"OnTime","Delayed"))) -> Delayed
A10: =Sales_data!A8 -> ORD10007 | B10: =Sales_data!H8 -> 20/03/2003 | C10: =IFERROR(DATEDIF(DATE(VALUE(RIGHT(B10,4)),VALUE(MID(B10,4,2)),VALUE(LEFT(B10,2))),TODAY(),"Y"),"") -> 23 | D10: =Sales_data!D8 -> 31/02/2025 | E10: =Sales_data!E8 -> 25/02/2026 | F10: =IF(E10="","",IFERROR(DATE(VALUE(RIGHT(E10,4)),VALUE(MID(E10,4,2)),VALUE(LEFT(E10,2)))-DATE(VALUE(RIGHT(D10,4)),VALUE(MID(D10,4,2)),VALUE(LEFT(D10,2))),"")) -> 359 | G10: =IF(E10="","Pending",IF(F10="","Pending",IF(F10<=5,"OnTime","Delayed"))) -> Delayed
A11: =Sales_data!A9 -> ORD10008 | B11: =Sales_data!H9 -> 07/03/1995 | C11: =IFERROR(DATEDIF(DATE(VALUE(RIGHT(B11,4)),VALUE(MID(B11,4,2)),VALUE(LEFT(B11,2))),TODAY(),"Y"),"") -> 31 | D11: =Sales_data!D9 -> 13/04/2025 | E11: =Sales_data!E9 -> 19/04/2025 | F11: =IF(E11="","",IFERROR(DATE(VALUE(RIGHT(E11,4)),VALUE(MID(E11,4,2)),VALUE(LEFT(E11,2)))-DATE(VALUE(RIGHT(D11,4)),VALUE(MID(D11,4,2)),VALUE(LEFT(D11,2))),"")) -> 6 | G11: =IF(E11="","Pending",IF(F11="","Pending",IF(F11<=5,"OnTime","Delayed"))) -> Delayed
A12: =Sales_data!A10 -> ORD10009 | B12: =Sales_data!H10 -> 06/04/1997 | C12: =IFERROR(DATEDIF(DATE(VALUE(RIGHT(B12,4)),VALUE(MID(B12,4,2)),VALUE(LEFT(B12,2))),TODAY(),"Y"),"") -> 29 | D12: =Sales_data!D10 -> 31/01/2026 | E12: =Sales_data!E10 -> 02/02/2026 | F12: =IF(E12="","",IFERROR(DATE(VALUE(RIGHT(E12,4)),VALUE(MID(E12,4,2)),VALUE(LEFT(E12,2)))-DATE(VALUE(RIGHT(D12,4)),VALUE(MID(D12,4,2)),VALUE(LEFT(D12,2))),"")) -> 2 | G12: =IF(E12="","Pending",IF(F12="","Pending",IF(F12<=5,"OnTime","Delayed"))) -> OnTime
A13: =Sales_data!A11 -> ORD10010 | B13: =Sales_data!H11 -> 07/01/1990 | C13: =IFERROR(DATEDIF(DATE(VALUE(RIGHT(B13,4)),VALUE(MID(B13,4,2)),VALUE(LEFT(B13,2))),TODAY(),"Y"),"") -> 36 | D13: =Sales_data!D11 -> 25/03/2025 | E13: =Sales_data!E11 -> 27/03/2025 | F13: =IF(E13="","",IFERROR(DATE(VALUE(RIGHT(E13,4)),VALUE(MID(E13,4,2)),VALUE(LEFT(E13,2)))-DATE(VALUE(RIGHT(D13,4)),VALUE(MID(D13,4,2)),VALUE(LEFT(D13,2))),"")) -> 2 | G13: =IF(E13="","Pending",IF(F13="","Pending",IF(F13<=5,"OnTime","Delayed"))) -> OnTime
A14: =Sales_data!A12 -> ORD10011 | B14: =Sales_data!H12 -> 10/05/1982 | C14: =IFERROR(DATEDIF(DATE(VALUE(RIGHT(B14,4)),VALUE(MID(B14,4,2)),VALUE(LEFT(B14,2))),TODAY(),"Y"),"") -> 44 | D14: =Sales_data!D12 -> 19/09/2025 | E14: =Sales_data!E12 -> 23/09/2025 | F14: =IF(E14="","",IFERROR(DATE(VALUE(RIGHT(E14,4)),VALUE(MID(E14,4,2)),VALUE(LEFT(E14,2)))-DATE(VALUE(RIGHT(D14,4)),VALUE(MID(D14,4,2)),VALUE(LEFT(D14,2))),"")) -> 4 | G14: =IF(E14="","Pending",IF(F14="","Pending",IF(F14<=5,"OnTime","Delayed"))) -> OnTime
A15: =Sales_data!A13 -> ORD10012 | B15: =Sales_data!H13 -> 23/01/1982 | C15: =IFERROR(DATEDIF(DATE(VALUE(RIGHT(B15,4)),VALUE(MID(B15,4,2)),VALUE(LEFT(B15,2))),TODAY(),"Y"),"") -> 44 | D15: =Sales_data!D13 -> 08/03/2025 | E15: =Sales_data!E13 -> 15/03/2025 | F15: =IF(E15="","",IFERROR(DATE(VALUE(RIGHT(E15,4)),VALUE(MID(E15,4,2)),VALUE(LEFT(E15,2)))-DATE(VALUE(RIGHT(D15,4)),VALUE(MID(D15,4,2)),VALUE(LEFT(D15,2))),"")) -> 7 | G15: =IF(E15="","Pending",IF(F15="","Pending",IF(F15<=5,"OnTime","Delayed"))) -> Delayed
... A503: =Sales_data!A501 -> ORD10500 | B503: =Sales_data!H501 -> 24/11/1976 | C503: =IFERROR(DATEDIF(DATE(VALUE(RIGHT(B503,4)),VALUE(MID(B503,4,2)),VALUE(LEFT(B503,2))),TODAY(),"Y"),"") -> 49 | D503: =Sales_data!D501 -> 16/09/2025 | E503: =Sales_data!E501 -> 23/09/2025 | F503: =IF(E503="","",IFERROR(DATE(VALUE(RIGHT(E503,4)),VALUE(MID(E503,4,2)),VALUE(LEFT(E503,2)))-DATE(VALUE(RIGHT(D503,4)),VALUE(MID(D503,4,2)),VALUE(LEFT(D503,2))),"")) -> 7 | G503: =IF(E503="","Pending",IF(F503="","Pending",IF(F503<=5,"OnTime","Delayed"))) -> Delayed

Sheet Product Lookup Report
A1: Q4 – Interactive Product Lookup System
A3: Enter Product ID | B3: P101
A4: Product Name | B4: =IFERROR(VLOOKUP($B$3,Product_master!$A$2:$F$11,2,0),"Product Not Found") -> Laptop
A5: Category | B5: =IFERROR(VLOOKUP($B$3,Product_master!$A$2:$F$11,3,0),"Product Not Found") -> Electronics
A6: Supplier | B6: =IFERROR(VLOOKUP($B$3,Product_master!$A$2:$F$11,4,0),"Product Not Found") -> TechHub
A7: Cost Price | B7: =IFERROR(VLOOKUP($B$3,Product_master!$A$2:$F$11,5,0),"Product Not Found") -> 41250
A8: Warranty (Months) | B8: =IFERROR(VLOOKUP($B$3,Product_master!$A$2:$F$11,6,0),"Product Not Found") -> 12
A11: Tip | B11: Change B3 to any Product ID (e.g., P202) to update the report automatically.

Sheet Sales Summary Report
A1: Q5 – Sales Performance Summary Report
A2: Metric | B2: Result
A3: 1. Electronics + Completed – Total Sales | B3: =SUMIFS(Sales_data!$P$2:$P$501,Sales_data!$K$2:$K$501,"Electronics",Sales_data!$V$2:$V$501,"Completed") -> 7222090
A4: 2. Neha + North – Total Sales | B4: =SUMIFS(Sales_data!$P$2:$P$501,Sales_data!$S$2:$S$501,"Neha",Sales_data!$J$2:$J$501,"North") -> 1550369.2
A5: 3. Orders: Discount >=15% + UPI | B5: =COUNTIFS(Sales_data!$O$2:$O$501,">=15%",Sales_data!$R$2:$R$501,"UPI") -> 83
A6: 4. Customers: Rating 5 + Completed | B6: =COUNTIFS(Sales_data!$Q$2:$Q$501,5,Sales_data!$V$2:$V$501,"Completed") -> 27
A7: 5. Average Sales: West + Quantity >5 | B7: =IFERROR(AVERAGEIFS(Sales_data!$P$2:$P$501,Sales_data!$J$2:$J$501,"West",Sales_data!$M$2:$M$501,">5"),0) -> 82824.451

Sheet Sales Statistics Report
A1: Q6 – Sales Statistics Report
A2: Statistic | B2: Formula Result
A3: Average Sales Amount | B3: =AVERAGE(Sales_data!$P$2:$P$501) -> 69531.875
A4: Median Sales Amount | B4: =MEDIAN(Sales_data!$P$2:$P$501) -> 10475
A5: Highest Sales Amount | B5: =MAX(Sales_data!$P$2:$P$501) -> 1045000
A6: Lowest Sales Amount | B6: =MIN(Sales_data!$P$2:$P$501) -> 19
A7: Standard Deviation (Sample) | B7: =STDEV(Sales_data!$P$2:$P$501) -> 167151.45
A8: 90th Percentile | B8: =PERCENTILE(Sales_data!$P$2:$P$501,0.9) -> 163880
A11: Meaning of 90th percentile | B11: 90% of the sales values are at or below this value; about 10% are above it.

Sheet Product Performance Report
A1: Q7 – Product Performance Analysis
A2: Metric | B2: Result
A3: Total Revenue (Quantity × Unit Price) | B3: =SUMPRODUCT(Sales_data!$M$2:$M$501,Sales_data!$N$2:$N$501) -> 36604875
A4: Weighted Average Unit Price | B4: =IFERROR(SUMPRODUCT(Sales_data!$M$2:$M$501,Sales_data!$N$2:$N$501)/SUM(Sales_data!$M$2:$M$501),0) -> 6989.6649
A5: Total Sales Column Value | B5: =SUM(Sales_data!$P$2:$P$501) -> 34765938
A6: Difference (Revenue – Sales) | B6: =B3-B5 -> 1838937.5
A7: Total Discounted Amount | B7: =SUMPRODUCT(Sales_data!$O$2:$O$501/100,Sales_data!$M$2:$M$501,Sales_data!$N$2:$N$501) -> 2918151.5

Sheet Financial Analysis Report
A1: Q8 – Financial Investment Analysis
A2: Calculation | B2: Result
A3: FV: ₹50,000/month, 5 years, 10% annual | B3: =FV(10%/12,5*12,-50000,0,0) -> 3871853.6
A4: Monthly investment for ₹50,00,000 target | B4: =PMT(10%/12,5*12,0,-5000000,0) -> 64568.557
A5: Monthly EMI: ₹10,00,000 loan, 9%, 5 years | B5: =PMT(9%/12,5*12,-1000000) -> 20758.355
A6: Rounded EMI | B6: =ROUND(ABS(B5),0) -> 20758
A7: Rounded Future Value | B7: =ROUND(B3,2) -> 3871853.6

Sheet Cleaned_Data
A1: Order_ID | B1: Customer_ID | C1: Product_ID | D1: Order_Date | E1: Delivery_Date | F1: Customer_Name | G1: Gender | H1: DOB | I1: City | J1: Region | K1: Category | L1: Product_Name | M1: Quantity | N1: Unit_Price | O1: Discount_% | P1: Sales | Q1: Rating | R1: Payment_Mode | S1: Salesperson | T1: Email | U1: Phone | V1: Order_Status | W1: Order Month
A2: ORD10001 | B2: C008 | C2: P202 | D2: 18/09/2025 | E2: 22/09/2025 | F2: Kavya Nair | G2: Female | H2: 01/08/1976 | I2: Hyderabad | J2: South | K2: Home Appliances | L2: Iron | M2: 4 | N2: 2200 | O2: 10 | P2: 7920 | Q2: 4 | R2: Cash | S2: Ritika | T2: KAvya.nair@company.com | U2: 9431429797 | V2: Completed | W2: 45901
A3: ORD10002 | B3: C008 | C3: P104 | D3: 27/04/2025 | E3: 04/05/2025 | F3: Kavya Nair | G3: Female | H3: 16/10/2000 | I3: Delhi | J3: North | K3: Electronics | L3: Monitor | M3: 17 | N3: 12000 | O3: 10 | P3: 183600 | Q3: 1 | R3: NetBanking | S3: Rahul | T3: kavya.nair@company.com | U3: 9129865339 | V3: Completed | W3: 45748
A4: ORD10003 | B4: C010 | C4: P101 | D4: 03/09/2025 | E4: 14/09/2025 | F4: Pooja Shah | G4: Female | H4: 16/09/1994 | I4: Bengaluru | J4: South | K4: Electronics | L4: Laptop | M4: 5 | N4: 55000 | O4: 5 | P4: 261250 | Q4: 3 | R4: NetBanking | S4: Aisha | T4: pooja.shah@company.com | U4: 9380975626 | V4: Pending | W4: 45901
A5: ORD10005 | B5: C009 | C5: P103 | D5: 27/09/2025 | E5: 07/10/2025 | F5: Mohit Verma | G5: Male | H5: 13/04/1976 | I5: Delhi | J5: North | K5: Electronics | L5: Keyboard | M5: 8 | N5: 1200 | O5: 5 | P5: 9120 | Q5: 2 | R5: Card | S5: Aisha | T5: mohit.verma@company.com | U5: 9724635978 | V5: Pending | W5: 45901
A6: ORD10006 | B6: C007 | C6: P202 | D6: 04/01/2026 | E6: 12/01/2026 | F6: Arjun Rao | G6: Male | H6: 07/02/1988 | I6: Hyderabad | J6: South | K6: Home Appliances | L6: Iron | M6: 4 | N6: 2200 | O6: 0 | P6: 8800 | Q6: 1 | R6: UPI | S6: Ritika | T6: arjun.rao@company.com | U6: 9780584905 | V6: Completed | W6: 46023
A7: ORD10007 | B7: C008 | C7: P201 | D7: 31/02/2025 | E7: 25/02/2026 | F7: Kavya Nair | G7: Female | H7: 20/03/2003 | I7: Hyderabad | J7: South | K7: Home Appliances | L7: Mixer | M7: 2 | N7: 3500 | O7: 5 | P7: 6650 | Q7: 1 | R7: UPI | S7: Ritika | T7: kavya.nair@company.com | U7: 9958252176 | V7: Completed
A8: ORD10008 | B8: C002 | C8: P104 | D8: 13/04/2025 | E8: 19/04/2025 | F8: Priya Patel | G8: Female | H8: 07/03/1995 | I8: Mumbai | J8: West | K8: Electronics | L8: Monitor | M8: 14 | N8: 12000 | O8: 15 | P8: 142800 | Q8: 4 | R8: NetBanking | S8: Ritika | T8: priYa.patel@company.com | U8: 9705521654 | V8: Completed | W8: 45748
A9: ORD10009 | B9: C008 | C9: P104 | D9: 31/01/2026 | E9: 02/02/2026 | F9: Kavya Nair | G9: Female | H9: 06/04/1997 | I9: Pune | J9: West | K9: Electronics | L9: Monitor | M9: 4 | N9: 12000 | O9: 15 | P9: 40800 | Q9: 4 | R9: UPI | S9: Neha | T9: kavya.nair@company.com | U9: 9588041011 | V9: Completed | W9: 46023
A10: ORD10010 | B10: C002 | C10: P301 | D10: 25/03/2025 | E10: 27/03/2025 | F10: Priya Patel | G10: Female | H10: 07/01/1990 | I10: Mumbai | J10: West | K10: Stationery | L10: Notebook | M10: 6 | N10: 60 | O10: 0 | P10: 360 | Q10: 4 | R10: Card | S10: Neha | T10: PRiya.patel@company.com | U10: 9340540608 | V10: Completed | W10: 45717
A11: ORD10011 | B11: C003 | C11: P202 | D11: 19/09/2025 | E11: 23/09/2025 | F11: Rohit Singh | G11: Male | H11: 10/05/1982 | I11: Delhi | J11: North | K11: Home Appliances | L11: Iron | M11: -3 | N11: 2200 | O11: 0 | P11: 35200 | Q11: 2 | R11: Card | S11: Rahul | T11: rohit.singh@company.com | U11: 9521710321 | V11: Pending | W11: 45901
A12: ORD10012 | B12: C008 | C12: P201 | D12: 08/03/2025 | E12: 15/03/2025 | F12: Kavya Nair | G12: Female | H12: 23/01/1982 | I12: Ahmedabad | J12: West | K12: Home Appliances | L12: Mixer | M12: 10 | N12: 3500 | O12: 5 | P12: 33250 | Q12: 5 | R12: Card | S12: Aisha | T12: kavya.nair@company.com | U12: 9123535241 | V12: Cancelled | W12: 45717
A13: ORD10013 | B13: C002 | C13: P202 | D13: 10/01/2025 | E13: 15/01/2025 | F13: Priya Patel | G13: Female | H13: 06/07/1992 | I13: Pune | J13: West | K13: Home Appliances | L13: Iron | M13: 15 | N13: 2200 | O13: 10 | P13: 29700 | Q13: 1 | R13: UPI | S13: Neha | T13: priya.patel@company.com | U13: 9367316892 | V13: Pending | W13: 45658
A14: ORD10014 | B14: C003 | C14: P202 | D14: 09/03/2025 | E14: 13/03/2025 | F14: Rohit Singh | G14: Male | H14: 19/03/2002 | I14: Mumbai | J14: West | K14: Home Appliances | L14: Iron | M14: 17 | N14: 2200 | O14: 5 | P14: 35530 | Q14: 1 | R14: Cash | S14: Karan | T14: rOhit.singh@company.com | U14: 9778489803 | V14: Completed | W14: 45717
A15: ORD10015 | B15: C008 | C15: P201 | D15: 26/07/2025 | E15: 07/08/2025 | F15: Kavya Nair | G15: Female | H15: 17/01/2001 | I15: Mumbai | J15: West | K15: Home Appliances | L15: Mixer | M15: 15 | N15: 3500 | O15: 15 | P15: 44625 | Q15: 2 | R15: Cash | S15: Neha | T15: kavya.nair@company.com | U15: 9582960180 | V15: Cancelled | W15: 45839
A16: ORD10016 | B16: C010 | C16: P103 | D16: 08/04/2026 | E16: 11/04/2026 | F16: Pooja Shah | G16: Female | H16: 11/04/2002 | I16: Hyderabad | J16: South | K16: Electronics | L16: Keyboard | M16: 3 | N16: 1200 | O16: 5 | P16: 3420 | Q16: 5 | R16: UPI | S16: Ritika | T16: pooja.shahcompany.com | U16: 9611394005 | V16: Completed | W16: 46113
A17: ORD10017 | B17: C004 | C17: P203 | D17: 22/02/2026 | E17: 03/03/2026 | F17: Amit Sharma | G17: Female | H17: 16/01/2002 | I17: Pune | J17: West | K17: Home Appliances | L17: Microwave | M17: 13 | N17: 8500 | O17: 20 | P17: 88400 | Q17: 4 | R17: Card | S17: Rahul | T17: anita.gupta@company.com | U17: 9692599404 | V17: Pending | W17: 46054
A18: ORD10018 | B18: C007 | C18: P203 | D18: 28/02/2026 | E18: 05/03/2026 | F18: Arjun Rao | G18: Male | H18: 09/10/1989 | I18: Ahmedabad | J18: West | K18: Home Appliances | L18: Microwave | M18: 4 | N18: 8500 | O18: 20 | P18: 27200 | Q18: 5 | R18: Card | S18: Aisha | T18: arjun.rao@company.com | U18: 9426119622 | V18: Pending | W18: 46054
A19: ORD10019 | B19: C007 | C19: P102 | D19: 01/12/2025 | E19: 04/12/2025 | F19: Arjun Rao | G19: Male | H19: 28/10/1991 | I19: Mumbai | J19: West | K19: Electronics | L19: Mouse | M19: 9 | N19: 700 | O19: 5 | P19: 5985 | Q19: 3 | R19: UPI | S19: Ritika | T19: arjun.Rao@company.com | U19: 9184436009 | V19: Pending | W19: 45992
... A73: ORD10073 | B73: C008 | C73: P103 | D73: 13/12/2025 | E73: 23/12/2025 | F73: Kavya Nair | G73: Female | H73: 22/09/1981 | I73: Jaipur | J73: North | K73: Electronics | L73: Keyboard | M73: 1 | N73: 1200 | O73: 5 | P73: 1140 | Q73: 3 | R73: UPI | S73: Aisha | T73: kavya.nair@company.com | U73: 9808988530 | V73: Cancelled | W73: 45992
A74: ORD10074 | B74: C010 | C74: P202 | D74: 04/02/2026 | E74: 16/02/2026 | F74: Pooja Shah | G74: Female | H74: 20/06/1980 | J74: South | K74: Home Appliances | L74: Iron | M74: 1 | N74: 2200 | O74: 15 | P74: 1870 | Q74: 4 | R74: Card | S74: Aisha | T74: pooja.shah@company.com | U74: 9286410494 | V74: Completed | W74: 46054
A75: ORD10075 | B75: C003 | C75: P103 | D75: 26/01/2026 | E75: 28/01/2026 | F75: Rohit Singh | G75: Male | H75: 02/11/1982 | I75: Pune | J75: West | K75: Electronics | L75: Keyboard | M75: 3 | N75: 1200 | O75: 10 | P75: 3240 | Q75: 5 | R75: Cash | S75: Rahul | T75: rohit.singh@company.com | U75: 9311555196 | V75: Completed | W75: 46023
A76: ORD10076 | B76: C008 | C76: P201 | D76: 27/06/2025 | E76: 07/07/2025 | F76: Kavya Nair | G76: Female | H76: 10/01/1980 | I76: Bengaluru | J76: South | K76: Home Appliances | L76: Mixer | M76: 10 | N76: 3500 | O76: 20 | P76: 28000 | Q76: 5 | R76: Card | S76: Ritika | T76: kavya.nair@company.com | U76: 9101810266 | V76: Completed | W76: 45809
A77: ORD10077 | B77: C007 | C77: P102 | D77: 17/03/2026 | E77: 19/03/2026 | F77: Arjun Rao | G77: Male | H77: 27/04/1981 | I77: Delhi | J77: North | K77: Electronics | L77: Mouse | M77: 18 | N77: 700 | O77: 5 | P77: 11970 | Q77: 3 | R77: Card | S77: Neha | T77: arjun.rao@company.com | U77: 9464556593 | V77: Cancelled | W77: 46082
A78: ORD10078 | B78: C005 | C78: P102 | D78: 09/06/2025 | E78: 18/06/2025 | F78: Vikas Mehta | G78: Male | H78: 12/03/1985 | I78: Bengaluru | J78: South | K78: Electronics | L78: Mouse | M78: 12 | N78: 700 | O78: 15 | P78: 7140 | Q78: 2 | R78: UPI | S78: Rahul | T78: vikas.mehta@company.com | U78: 9338278358 | V78: Completed | W78: 45809
A79: ORD10079 | B79: C009 | C79: P103 | D79: 15/11/2025 | E79: 16/11/2025 | F79: Mohit Verma | G79: Male | H79: 15/03/1999 | I79: Mumbai | J79: West | K79: Electronics | L79: Keyboard | M79: 8 | N79: 1200 | O79: 0 | P79: 9600 | Q79: 4 | R79: Card | S79: Rahul | T79: mohit.verma@company.com | U79: 9621410770 | V79: Pending | W79: 45962
A80: ORD10080 | B80: C003 | C80: P301 | D80: 06/11/2025 | E80: 10/11/2025 | F80: Rohit Singh | G80: Male | H80: 07/07/1983 | I80: Pune | J80: West | K80: Stationery | L80: Notebook | M80: 2 | N80: 60 | O80: 0 | P80: 120 | Q80: 2 | R80: UPI | S80: Rahul | T80: rohit.singh@company.com | U80: 9981333189 | V80: Completed | W80: 45962
A81: ORD10081 | B81: C001 | C81: P303 | D81: 01/01/2025 | E81: 07/01/2025 | F81: Amit Sharma | G81: Male | H81: 06/03/1989 | I81: Pune | J81: West | K81: Stationery | L81: Marker | M81: 10 | N81: 45 | O81: 15 | P81: 382.5 | Q81: 3 | R81: NetBanking | S81: Ritika | T81: amit.sharma@company.com | U81: 9723450355 | V81: Cancelled | W81: 45658
A82: ORD10082 | B82: C005 | C82: P201 | D82: 25/04/2026 | E82: 03/05/2026 | F82: Vikas Mehta | G82: Male | H82: 20/06/1982 | I82: Kolkata | J82: East | K82: Home Appliances | L82: Mixer | M82: 12 | N82: 3500 | O82: 5 | P82: 39900 | Q82: 3 | R82: NetBanking | S82: Aisha | T82: vikas.mehta@company.com | U82: 9886243907 | V82: Pending | W82: 46113
A83: ORD10083 | B83: C003 | C83: P301 | D83: 19/09/2025 | E83: 27/09/2025 | F83: Rohit Singh | G83: Male | H83: 23/06/2001 | I83: Mumbai | J83: West | K83: Stationery | L83: Notebook | M83: 2 | N83: 60 | O83: 15 | P83: 102 | Q83: 1 | R83: UPI | S83: Neha | T83: rohit.singh@company.com | U83: 9473931904 | V83: Completed | W83: 45901
A84: ORD10084 | B84: C003 | C84: P103 | D84: 18/03/2025 | E84: 21/03/2025 | F84: Rohit Singh | G84: Male | H84: 19/07/1983 | I84: Hyderabad | J84: South | K84: Electronics | L84: Keyboard | M84: 18 | N84: 1200 | O84: 15 | P84: 18360 | Q84: 3 | R84: Card | S84: Neha | T84: rohit.singh@company.com | U84: 9287159610 | V84: Pending | W84: 45717
A85: ORD10085 | B85: C008 | C85: P104 | D85: 30/10/2025 | E85: 31/10/2025 | F85: Kavya Nair | G85: Female | H85: 24/03/1993 | I85: Mumbai | J85: West | K85: Electronics | L85: Monitor | M85: 18 | N85: 12000 | O85: 15 | P85: 183600 | Q85: 2 | R85: Cash | S85: Rahul | T85: kavya.nair@company.com | U85: 9876513858 | V85: Completed | W85: 45931
A86: ORD10086 | B86: C007 | C86: P302 | D86: 31/10/2025 | E86: 11/11/2025 | F86: Arjun Rao | G86: Male | H86: 10/05/1995 | I86: Ahmedabad | J86: West | K86: Stationery | L86: Pen | M86: 7 | N86: 20 | O86: 0 | P86: 140 | Q86: 2 | R86: Card | S86: Ritika | T86: arjun.rao@company.com | U86: 9237400853 | V86: Cancelled | W86: 45931
... A118: ORD10118 | B118: C001 | C118: P303 | D118: 31/05/2025 | E118: 11/06/2025 | F118: Amit Sharma | G118: Male | H118: 07/09/1995 | I118: Pune | J118: West | K118: Stationery | L118: Marker | M118: 16 | N118: 45 | O118: 0 | P118: 720 | Q118: 1 | R118: NetBanking | S118: Aisha | T118: amit.sharma@company.com | U118: 9807154421 | V118: Completed | W118: 45778
A119: ORD10119 | B119: C009 | C119: P103 | D119: 30/05/2025 | E119: 02/06/2025 | F119: Mohit Verma | G119: Male | H119: 08/03/1988 | I119: Ahmedabad | J119: West | K119: Electronics | L119: Keyboard | M119: Ten | N119: 1200 | O119: 15 | P119: 7140 | Q119: 4 | R119: UPI | S119: Karan | T119: mohit.verma@company.com | U119: 9919834000 | V119: Pending | W119: 45778
A120: ORD10120 | B120: C002 | C120: P104 | D120: 19/08/2025 | E120: 30/08/2025 | F120: Priya Patel | G120: Female | H120: 07/07/1989 | I120: Jaipur | J120: North | K120: Electronics | L120: Monitor | M120: 14 | N120: 12000 | O120: 15 | P120: 142800 | Q120: 2 | R120: NetBanking | S120: Aisha | T120: priya.patel@company.com | U120: 9739798818 | V120: Pending | W120: 45870
A121: ORD10121 | B121: C003 | C121: P203 | D121: 14/12/2025 | E121: 16/12/2025 | F121: Rohit Singh | G121: Male | H121: 11/11/1993 | I121: Pune | J121: West | K121: Home Appliances | L121: Microwave | M121: 8 | N121: 8500 | O121: 20 | P121: 54400 | Q121: 3 | R121: Card | S121: Rahul | T121: rohit.singh@company.com | U121: 9208625306 | V121: Completed | W121: 45992
A122: ORD10122 | B122: C007 | C122: P303 | D122: 31/01/2026 | E122: 10/02/2026 | F122: Arjun Rao | G122: Male | H122: 01/02/2000 | I122: Bengaluru | J122: South | K122: Stationery | L122: Marker | M122: 3 | N122: 45 | O122: 0 | P122: 135 | Q122: 4 | R122: UPI | S122: Aisha | T122: arjun.rao@company.com | U122: 9970178536 | V122: Cancelled | W122: 46023
A123: ORD10123 | B123: C001 | C123: P102 | D123: 03/01/2026 | E123: 04/01/2026 | F123: Amit Sharma | G123: Male | H123: 22/06/1986 | I123: Jaipur | J123: North | K123: Electronics | L123: Mouse | M123: 13 | N123: 700 | O123: 5 | P123: 8645 | Q123: 3 | R123: Card | S123: Neha | T123: amit.sharma@company.com | U123: 9633745195 | V123: Pending | W123: 46023
A124: ORD10124 | B124: C004 | C124: P103 | D124: 20/10/2025 | E124: 26/10/2025 | F124: Anita Gupta | G124: Female | H124: 16/02/1986 | I124: Mumbai | J124: West | K124: Electronics | L124: Keyboard | M124: 14 | N124: 1200 | O124: 20 | P124: 13440 | Q124: 5 | R124: NetBanking | S124: Aisha | T124: anita.gupta@company.com | U124: 9922102053 | V124: Completed | W124: 45931
A125: ORD10125 | B125: C002 | C125: P303 | D125: 11/05/2025 | E125: 21/05/2025 | F125: Priya Patel | G125: Female | H125: 18/09/1991 | I125: Delhi | J125: North | K125: Stationery | L125: Marker | M125: 2 | N125: 45 | O125: 5 | P125: 85.5 | Q125: 3 | R125: UPI | S125: Ritika | T125: priya.patel@company.com | U125: 9135963930 | V125: Cancelled | W125: 45778
A126: ORD10126 | B126: C004 | C126: P103 | D126: 02/01/2026 | E126: 06/01/2026 | F126: Anita Gupta | G126: Female | H126: 04/01/1981 | I126: Bengaluru | J126: South | K126: Electronics | L126: Keyboard | M126: 2 | N126: 1200 | O126: 20 | P126: 1920 | Q126: 3 | R126: Card | S126: Neha | T126: anita.gupta@company.com | U126: 9429405275 | V126: Completed | W126: 46023
A127: ORD10127 | B127: C003 | C127: P101 | D127: 20/04/2026 | E127: 26/04/2026 | F127: Rohit Singh | G127: Male | H127: 12/10/2004 | I127: Bengaluru | J127: South | K127: Electronics | L127: Laptop | M127: 10 | N127: 55000 | O127: 5 | P127: 522500 | Q127: 5 | R127: UPI | S127: Aisha | T127: rohit.singh@company.com | U127: 9521757571 | V127: Pending | W127: 46113
A128: ORD10128 | B128: C006 | C128: P201 | D128: 04/08/2025 | E128: 05/08/2025 | F128: Sneha Joshi | G128: Female | H128: 25/03/1984 | I128: Jaipur | J128: North | K128: Home Appliances | L128: Mixer | M128: 15 | N128: 3500 | O128: 10 | P128: 47250 | Q128: 3 | R128: NetBanking | S128: Neha | T128: sneha.joshi@company.com | U128: 9467375455 | V128: Completed | W128: 45870
A129: ORD10129 | B129: C002 | C129: P202 | D129: 13/08/2025 | E129: 18/08/2025 | F129: Priya Patel | G129: Female | H129: 09/09/1982 | I129: Bengaluru | J129: South | K129: Home Appliances | L129: Iron | M129: 10 | N129: 2200 | O129: 15 | P129: 18700 | Q129: 4 | R129: Card | S129: Rahul | T129: priya.patel@company.com | U129: 9838809695 | V129: Pending | W129: 45870
A130: ORD10130 | B130: C006 | C130: P201 | D130: 16/06/2025 | E130: 24/06/2025 | F130: Sneha Joshi | G130: Female | H130: 15/02/1993 | I130: Pune | J130: West | K130: Home Appliances | L130: Mixer | M130: 11 | N130: 3500 | O130: 5 | P130: 36575 | Q130: 5 | R130: Cash | S130: Ritika | T130: sneha.joshi@company.com | U130: 9296609782 | V130: Cancelled | W130: 45809
A131: ORD10131 | B131: C004 | C131: P103 | D131: 27/04/2026 | E131: 30/04/2026 | F131: Anita Gupta | G131: Female | H131: 08/04/2003 | I131: Bengaluru | J131: South | K131: Electronics | L131: Keyboard | M131: 14 | N131: 1200 | O131: 0 | P131: 16800 | Q131: 5 | R131: Cash | S131: Rahul | T131: anita.gupta@company.com | U131: 9848259992 | V131: Cancelled | W131: 46113
... A355: ORD10356 | B355: C008 | C355: P303 | D355: 11/10/2025 | E355: 21/10/2025 | F355: Kavya Nair | G355: Female | H355: 22/05/1992 | I355: Jaipur | J355: North | K355: Stationery | L355: Marker | M355: 5 | N355: 45 | O355: 5 | P355: 213.75 | Q355: 1 | R355: Card | S355: Neha | T355: kavya.nair@company.com | U355: 9810433484 | V355: Completed | W355: 45931
A356: ORD10357 | B356: C006 | C356: P102 | D356: \ | E356: 11/02/2025 | F356: Sneha Joshi | G356: Female | H356: 10/11/1989 | I356: Mumbai | J356: West | K356: Electronics | L356: Mouse | M356: 3 | N356: 700 | O356: 15 | P356: 1785 | Q356: 4 | R356: Cash | S356: Karan | T356: sneha.joshi@company.com | U356: 9990243436 | V356: Completed
A357: ORD10358 | B357: C009 | C357: P203 | D357: 14/12/2025 | E357: 26/12/2025 | F357: Mohit Verma | G357: Male | H357: 03/09/1980 | I357: Jaipur | J357: North | K357: Home Appliances | L357: Microwave | M357: 12 | N357: 8500 | O357: 5 | P357: 96900 | Q357: 3 | R357: Card | S357: Aisha | T357: mohit.verma@company.com | U357: 9396678031 | V357: Pending | W357: 45992
A358: ORD10359 | B358: C006 | C358: P203 | D358: 11/04/2026 | E358: 19/04/2026 | F358: Sneha Joshi | G358: Female | H358: 06/03/1979 | I358: Pune | J358: West | K358: Home Appliances | L358: Microwave | M358: 4 | N358: 8500 | O358: 15 | P358: 28900 | Q358: 4 | R358: NetBanking | S358: Aisha | T358: sneha.joshi@company.com | U358: 9818591245 | V358: Pending | W358: 46113
A359: ORD10360 | B359: C003 | C359: P302 | D359: 19/04/2025 | E359: 22/04/2025 | F359: Rohit Singh | G359: Male | H359: 04/09/1996 | I359: Jaipur | J359: North | K359: Stationery | L359: Pen | M359: 16 | N359: 20 | O359: 10 | P359: 288 | Q359: 4 | R359: Cash | S359: Neha | T359: rohit.singh@company.com | U359: 9505550047 | V359: Cancelled | W359: 45748
A360: ORD10361 | B360: C003 | C360: P301 | D360: 10/05/2026 | E360: 18/05/2026 | F360: Rohit Singh | G360: Male | H360: 14/03/1999 | I360: Mumbai | J360: West | K360: Stationery | L360: Notebook | M360: 3 | N360: 60 | O360: 20 | P360: 144 | Q360: 4 | R360: UPI | S360: Karan | T360: rohit.singh@company.com | U360: 9469828772 | V360: Pending | W360: 46143
A361: ORD10362 | B361: C009 | C361: P202 | D361: 20/07/2025 | E361: 26/07/2025 | F361: Mohit Verma | G361: Male | H361: 03/10/1984 | I361: Mumbai | J361: West | K361: Home Appliances | L361: Iron | M361: 19 | N361: 2200 | O361: 10 | P361: 37620 | Q361: 2 | R361: Cash | S361: Karan | T361: mohit.verma@company.com | U361: 9885092680 | V361: Pending | W361: 45839
A362: ORD10363 | B362: C009 | C362: P103 | D362: 23/01/2026 | E362: 27/01/2026 | F362: Mohit Verma | G362: Male | H362: 09/07/1984 | I362: Hyderabad | J362: South | K362: Electronics | L362: Keyboard | M362: 7 | N362: 1200 | O362: 20 | P362: 6720 | Q362: 3 | R362: Card | S362: Neha | T362: mohit.verma@company.com | U362: 9362319457 | V362: Cancelled | W362: 46023
A363: ORD10364 | B363: C010 | C363: P302 | D363: 16/03/2026 | E363: 21/03/2026 | F363: Pooja Shah | G363: Female | H363: 10/03/1989 | I363: Bengaluru | J363: South | K363: Stationery | L363: Pen | M363: 20 | N363: 20 | O363: 20 | P363: 320 | Q363: 5 | R363: Card | S363: Neha | T363: pooja.shah@company.com | U363: 9223945130 | V363: Pending | W363: 46082
A364: ORD10365 | B364: C002 | C364: P103 | D364: 30/04/2025 | E364: 07/05/2025 | F364: Priya Patel | G364: Female | H364: 19/04/1985 | I364: Hyderabad | J364: South | K364: Electronics | L364: Keyboard | M364: 19 | N364: 1200 | O364: 5 | P364: 21660 | Q364: 3 | R364: Card | S364: Ritika | T364: priya.patel@company.com | U364: 9910804926 | V364: Pending | W364: 45748
A365: ORD10366 | B365: C010 | C365: P302 | D365: 03/02/2025 | E365: 13/02/2025 | F365: Pooja Shah | G365: Female | H365: 13/08/2003 | I365: Hyderabad | J365: South | K365: Stationery | L365: Pen | M365: 5 | N365: 20 | O365: 0 | P365: 100 | Q365: 2 | R365: UPI | S365: Rahul | T365: pooja.shah@company.com | U365: 9274269744 | V365: Pending | W365: 45689
A366: ORD10367 | B366: C002 | C366: P303 | D366: 07/03/2026 | E366: 16/03/2026 | F366: Priya Patel | G366: Female | H366: 11/09/1983 | I366: Jaipur | J366: North | K366: Stationery | L366: Marker | M366: 16 | N366: 45 | O366: 15 | P366: 612 | Q366: 5 | R366: Cash | S366: Aisha | T366: priya.patel@company.com | U366: 9223196101 | V366: Cancelled | W366: 46082
A367: ORD10368 | B367: C008 | C367: P202 | D367: 03/05/2025 | E367: 15/05/2025 | F367: Kavya Nair | G367: Female | H367: 11/06/1976 | I367: Jaipur | J367: North | K367: Home Appliances | L367: Iron | M367: 1 | N367: 2200 | O367: 10 | P367: 1980 | Q367: 5 | R367: Card | S367: Rahul | T367: kavya.nair@company.com | U367: 9888477457 | V367: Completed | W367: 45778
A368: ORD10369 | B368: C010 | C368: P301 | D368: 01/04/2026 | E368: 05/04/2026 | F368: Pooja Shah | G368: Female | H368: 04/01/1987 | I368: Hyderabad | J368: South | K368: Stationery | L368: Notebook | M368: 19 | N368: 60 | O368: 15 | P368: 969 | Q368: 4 | R368: NetBanking | S368: Neha | T368: pooja.shah@company.com | U368: 9435947486 | V368: Cancelled | W368: 46113
A369: ORD10370 | B369: C001 | C369: P101 | D369: Pending | E369: 02/02/2025 | F369: Amit Sharma | G369: Male | H369: 14/05/1992 | I369: Delhi | J369: North | K369: Electronics | L369: Laptop | M369: 15 | N369: 55000 | O369: 0 | P369: 825000 | Q369: 5 | R369: Card | S369: Neha | T369: amit.sharma@company.com | U369: 9411668831 | V369: Cancelled
A370: ORD10371 | B370: C009 | C370: P303 | D370: 06/10/2025 | E370: 08/10/2025 | F370: Mohit Verma | G370: Male | H370: 03/05/1989 | I370: Bengaluru | J370: South | K370: Stationery | L370: Marker | M370: 11 | N370: 45 | O370: 5 | P370: 470.25 | Q370: 5 | R370: NetBanking | S370: Karan | T370: mohit.verma@company.com | U370: 9523682403 | V370: Completed | W370: 45931
A371: ORD10372 | B371: C006 | C371: P302 | D371: 12/06/2025 | E371: 17/06/2025 | F371: Sneha Joshi | G371: Female | H371: 19/12/1990 | I371: Jaipur | J371: North | K371: Stationery | L371: Pen | M371: 9 | N371: 20 | O371: 10 | P371: 162 | Q371: 1 | R371: Card | S371: Rahul | T371: sneha.joshi@company.com | U371: 9652936744 | V371: Cancelled | W371: 45809
A372: ORD10373 | B372: C004 | C372: P303 | D372: 18/11/2025 | E372: 20/11/2025 | F372: Anita Gupta | G372: Female | H372: 09/07/1995 | I372: Bengaluru | J372: South | K372: Stationery | L372: Marker | M372: 5 | N372: 45 | O372: 5 | P372: 213.75 | Q372: 3 | R372: Card | S372: Neha | T372: anita.gupta@company.com | U372: 9726464733 | V372: Pending | W372: 45962
A373: ORD10374 | B373: C007 | C373: P102 | D373: 01/11/2025 | E373: 02/11/2025 | F373: Arjun Rao | G373: Male | H373: 23/12/1998 | I373: Hyderabad | J373: South | K373: Electronics | L373: Mouse | M373: 5 | N373: 700 | O373: 10 | P373: 3150 | Q373: 2 | R373: UPI | S373: Rahul | T373: arjun.rao@company.com | U373: 9273520544 | V373: Completed | W373: 45962
A374: ORD10375 | B374: C005 | C374: P102 | D374: 24/01/2025 | E374: 31/01/2025 | F374: Vikas Mehta | G374: Male | H374: 23/12/1979 | I374: Kolkata | J374: East | K374: Electronics | L374: Mouse | M374: 1 | N374: 700 | O374: 0 | P374: 700 | Q374: 1 | R374: UPI | S374: Karan | T374: vikas.mehta@company.com | U374: 9374259988 | V374: Completed | W374: 45658
A375: ORD10376 | B375: C008 | C375: P102 | D375: 13/02/2026 | E375: 21/02/2026 | F375: Kavya Nair | G375: Female | H375: 15/12/1975 | I375: Mumbai | J375: West | K375: Electronics | L375: Mouse | M375: 13 | N375: 700 | O375: 20 | P375: 7280 | Q375: 2 | R375: Card | S375: Ritika | T375: kavya.nair@company.com | U375: 9538129419 | V375: Completed | W375: 46054
A376: ORD10377 | B376: C009 | C376: P104 | D376: 08/02/2025 | E376: 19/02/2025 | F376: Mohit Verma | G376: Male | H376: 17/05/1993 | I376: Pune | J376: West | K376: Electronics | L376: Monitor | M376: 20 | N376: 12000 | O376: 0 | P376: 240000 | Q376: 2 | R376: Card | S376: Neha | T376: mohit.verma@company.com | U376: 9382815686 | V376: Completed | W376: 45689
A377: ORD10378 | B377: C007 | C377: P103 | D377: 28/12/2025 | E377: 06/01/2026 | F377: Arjun Rao | G377: Male | H377: 17/09/1976 | I377: Kolkata | J377: East | K377: Electronics | L377: Keyboard | M377: 9 | N377: 1200 | O377: 15 | P377: 9180 | Q377: 1 | R377: UPI | S377: Ritika | T377: arjun.rao@company.com | U377: 9450746157 | V377: Pending | W377: 45992
A378: ORD10379 | B378: C007 | C378: P302 | D378: 01/10/2025 | E378: 03/10/2025 | F378: Arjun Rao | G378: Male | H378: 22/12/1996 | I378: Jaipur | J378: North | K378: Stationery | L378: Pen | M378: 3 | N378: 20 | O378: 15 | P378: 51 | Q378: 3 | R378: Cash | S378: Neha | T378: arjun.rao@company.com | U378: 9349012570 | V378: Pending | W378: 45931
A379: ORD10380 | B379: C006 | C379: P101 | D379: 18/12/2025 | E379: 19/12/2025 | F379: Sneha Joshi | G379: Female | H379: 25/12/1995 | I379: Delhi | J379: North | K379: Electronics | L379: Laptop | M379: 8 | N379: 55000 | O379: 20 | P379: 352000 | Q379: 5 | R379: Card | S379: Karan | T379: sneha.joshi@company.com | U379: 9442163790 | V379: Pending | W379: 45992
A380: ORD10381 | B380: C006 | C380: P301 | D380: 29/09/2025 | E380: 07/10/2025 | F380: Sneha Joshi | G380: Female | H380: 23/06/1985 | I380: Delhi | J380: North | K380: Stationery | L380: Notebook | M380: 17 | N380: 60 | O380: 20 | P380: 816 | Q380: 1 | R380: UPI | S380: Ritika | T380: sneha.joshi@company.com | U380: 9953329223 | V380: Pending | W380: 45901
A381: ORD10382 | B381: C003 | C381: P302 | D381: 14/05/2025 | E381: 22/05/2025 | F381: Rohit Singh | G381: Male | H381: 10/02/1984 | I381: Bengaluru | J381: South | K381: Stationery | L381: Pen | M381: 4 | N381: 20 | O381: 15 | P381: 68 | Q381: 3 | R381: NetBanking | S381: Aisha | T381: rohit.singh@company.com | U381: 9202321359 | V381: Pending | W381: 45778
... A397: ORD10398 | B397: C007 | C397: P104 | D397: 31/01/2025 | E397: 04/02/2025 | F397: Arjun Rao | G397: Male | H397: 10/12/1978 | I397: Kolkata | J397: East | K397: Electronics | L397: Monitor | M397: 19 | N397: 12000 | O397: 0 | P397: 228000 | Q397: 4 | R397: UPI | S397: Aisha | T397: arjun.rao@company.com | U397: 9136906750 | V397: Pending | W397: 45658
A398: ORD10399 | B398: C001 | C398: P102 | D398: Pending | E398: 03/11/2025 | F398: Amit Sharma | G398: Male | H398: 01/09/1979 | I398: Bengaluru | J398: South | K398: Electronics | L398: Mouse | M398: 12 | N398: 700 | O398: 15 | P398: 7140 | Q398: 3 | R398: Card | S398: Ritika | T398: amit.sharma@company.com | U398: 9485286324 | V398: Completed
A399: ORD10400 | B399: C008 | C399: P103 | D399: 13/05/2025 | E399: 21/05/2025 | F399: Kavya Nair | G399: Female | H399: 08/04/2001 | I399: Delhi | J399: North | K399: Electronics | L399: Keyboard | M399: 16 | N399: 1200 | O399: 20 | P399: 15360 | Q399: 1 | R399: Cash | S399: Rahul | T399: kavya.nair@company.com | U399: 9414633966 | V399: Pending | W399: 45778
A400: ORD10401 | B400: C009 | C400: P203 | D400: 27/12/2025 | E400: 04/01/2026 | F400: Mohit Verma | G400: Male | H400: 01/01/1983 | I400: Hyderabad | J400: South | K400: Home Appliances | L400: Microwave | M400: 10 | N400: 8500 | O400: 5 | P400: 80750 | Q400: 5 | R400: NetBanking | S400: Ritika | T400: mohit.verma@company.com | U400: 9833735234 | V400: Completed | W400: 45992
A401: ORD10402 | B401: C008 | C401: P302 | D401: 11/02/2025 | E401: 21/02/2025 | F401: Kavya Nair | G401: Female | H401: 09/08/1989 | I401: Ahmedabad | J401: West | K401: Stationery | L401: Pen | M401: 18 | N401: 20 | O401: 20 | P401: 288 | Q401: 1 | R401: UPI | S401: Ritika | T401: kavya.nair@company.com | U401: 9523689108 | V401: Pending | W401: 45689
A402: ORD10403 | B402: C009 | C402: P203 | D402: 13/03/2026 | E402: 19/03/2026 | F402: Mohit Verma | G402: Male | H402: 22/10/1993 | I402: Mumbai | J402: West | K402: Home Appliances | L402: Microwave | M402: 9 | N402: 8500 | O402: 0 | P402: 76500 | Q402: 2 | R402: Card | S402: Ritika | T402: mohit.verma@company.com | U402: 9812909831 | V402: Pending | W402: 46082
A403: ORD10404 | B403: C008 | C403: P203 | D403: 01/10/2025 | E403: 12/10/2025 | F403: Kavya Nair | G403: Female | H403: 05/05/2000 | I403: Mumbai | J403: West | K403: Home Appliances | L403: Microwave | M403: 8 | N403: 8500 | O403: 10 | P403: 61200 | Q403: 4 | R403: Cash | S403: Neha | T403: kavya.nair@company.com | U403: 9106290987 | V403: Cancelled | W403: 45931
A404: ORD10405 | B404: C010 | C404: P302 | D404: 26/01/2026 | E404: 01/02/2026 | F404: Pooja Shah | G404: Female | H404: 18/02/1984 | I404: Pune | J404: West | K404: Stationery | L404: Pen | M404: 3 | N404: 20 | O404: 10 | P404: 54 | Q404: 3 | R404: Card | S404: Karan | T404: pooja.shah@company.com | U404: 9767727724 | V404: Pending | W404: 46023
A405: ORD10406 | B405: C004 | C405: P203 | D405: 02/07/2025 | E405: 12/07/2025 | F405: Anita Gupta | G405: Female | H405: 13/06/1991 | I405: Kolkata | J405: East | K405: Home Appliances | L405: Microwave | M405: 18 | N405: 8500 | O405: 10 | P405: 137700 | Q405: 4 | R405: Cash | S405: Rahul | T405: anita.gupta@company.com | U405: 9865401727 | V405: Cancelled | W405: 45839
A406: ORD10407 | B406: C010 | C406: P303 | D406: 05/10/2025 | E406: 09/10/2025 | F406: Pooja Shah | G406: Female | H406: 19/05/1996 | I406: Pune | J406: West | K406: Stationery | L406: Marker | M406: 5 | N406: 45 | O406: 10 | P406: 202.5 | Q406: 3 | R406: Cash | S406: Neha | T406: pooja.shah@company.com | U406: 9603848571 | V406: Pending | W406: 45931
A407: ORD10408 | B407: C009 | C407: P303 | D407: 30/05/2025 | E407: 02/06/2025 | F407: Mohit Verma | G407: Male | H407: 23/05/1992 | I407: Mumbai | J407: West | K407: Stationery | L407: Marker | M407: 2 | N407: 45 | O407: 20 | P407: 72 | Q407: 5 | R407: UPI | S407: Aisha | T407: mohit.verma@company.com | U407: 9101231789 | V407: Cancelled | W407: 45778
A408: ORD10409 | B408: C002 | C408: P303 | D408: 27/01/2025 | E408: 06/02/2025 | F408: Priya Patel | G408: Female | H408: 15/06/1988 | I408: Hyderabad | J408: South | K408: Stationery | L408: Marker | M408: 18 | N408: 45 | O408: 10 | P408: 729 | Q408: 2 | R408: NetBanking | S408: Neha | T408: priya.patel@company.com | U408: 9485017802 | V408: Pending | W408: 45658
A409: ORD10410 | B409: C003 | C409: P103 | D409: 24/12/2025 | E409: 01/01/2026 | F409: Rohit Singh | G409: Male | H409: 22/07/1993 | I409: Kolkata | J409: East | K409: Electronics | L409: Keyboard | M409: 13 | N409: 1200 | O409: 5 | P409: 14820 | Q409: 4 | R409: Card | S409: Neha | T409: rohit.singh@company.com | U409: 9815464650 | V409: Completed | W409: 45992
A410: ORD10411 | B410: C008 | C410: P302 | D410: 11/05/2026 | E410: 17/05/2026 | F410: Kavya Nair | G410: Female | H410: 03/02/2004 | I410: Hyderabad | J410: South | K410: Stationery | L410: Pen | M410: 14 | N410: 20 | O410: 20 | P410: 224 | Q410: 5 | R410: UPI | S410: Rahul | T410: kavya.nair@company.com | U410: 9860715839 | V410: Pending | W410: 46143
... A499: ORD10500 | B499: C002 | C499: P201 | D499: 16/09/2025 | E499: 23/09/2025 | F499: Priya Patel | G499: Female | H499: 24/11/1976 | I499: Bengaluru | J499: South | K499: Home Appliances | L499: Mixer | M499: 20 | N499: 3500 | O499: 0 | P499: 70000 | Q499: 1 | R499: NetBanking | S499: Karan | T499: priya.patel@company.com | U499: 9810334941 | V499: Pending | W499: 45901

Sheet Dashboard Data
A1: Dashboard Pivot-style Source Data
A3: Filter | D3: Filter | G3: Filter | J3: KPI | K3: Value
J4: Total Sales | K4: =SUM(Cleaned_Data!$P$2:$P$499) -> 34745968
A5: Region | B5: Sum - Sales | D5: Category | E5: Sum - Sales | G5: Order Month | H5: Sum - Sales | J5: Total Orders | K5: =COUNTA(Cleaned_Data!$A$2:$A$499) -> 498
A6: East | B6: 4041922 | D6: Electronics | E6: 27823939 | G6: 45658 | H6: 2274817.5 | J6: Average Sales per Order | K6: =IFERROR(K4/K5,0) -> 69771.019
A7: North | B7: 10013332 | D7: Home Appliances | E7: 6806525 | G7: 45689 | H7: 3868013.8
A8: South | B8: 7487181.5 | D8: Stationery | E8: 115503.5 | G8: 45717 | H8: 1303035.2
A9: West | B9: 13203532 | D9: Total Result | E9: 34745968 | G9: 45748 | H9: 3042603.8
A10: Total Result | B10: 34745968 | G10: 45778 | H10: 3134828.5
G11: 45809 | H11: 1032385
G12: 45839 | H12: 1741047.5
G13: 45870 | H13: 1836526
G14: 45901 | H14: 1226591.5
G15: 45931 | H15: 1775603.5
G16: 45962 | H16: 1992715.2
G17: 45992 | H17: 2185859.5
G18: 46023 | H18: 2304380
G19: 46054 | H19: 487533.5
G20: 46082 | H20: 2337934.5
G21: 46113 | H21: 2647114
G22: 46143 | H22: 714403.5
G23: (empty) | H23: 840575
G24: Total Result | H24: 34745968
G25: 46296 | H25: =SUMPRODUCT((IFERROR(DATE(VALUE(RIGHT(Cleaned_Data!$D$2:$D$499,4)),VALUE(MID(Cleaned_Data!$D$2:$D$499,4,2)),VALUE(LEFT(Cleaned_Data!$D$2:$D$499,2))),0)>=DATE(YEAR(G25),MONTH(G25),1))*(IFERROR(DATE(VALUE(RIGHT(Cleaned_Data!$D$2:$D$499,4)),VALUE(MID(Cleaned_Data!$D$2:$D$499,4,2)),VALUE(LEFT(Cleaned_Data!$D$2:$D$499,2))),0)<EDATE(G25,1))*Cleaned_Data!$P$2:$P$499) -> 0
G26: 46327 | H26: =SUMPRODUCT((IFERROR(DATE(VALUE(RIGHT(Cleaned_Data!$D$2:$D$499,4)),VALUE(MID(Cleaned_Data!$D$2:$D$499,4,2)),VALUE(LEFT(Cleaned_Data!$D$2:$D$499,2))),0)>=DATE(YEAR(G26),MONTH(G26),1))*(IFERROR(DATE(VALUE(RIGHT(Cleaned_Data!$D$2:$D$499,4)),VALUE(MID(Cleaned_Data!$D$2:$D$499,4,2)),VALUE(LEFT(Cleaned_Data!$D$2:$D$499,2))),0)<EDATE(G26,1))*Cleaned_Data!$P$2:$P$499) -> 0
G27: 46357 | H27: =SUMPRODUCT((IFERROR(DATE(VALUE(RIGHT(Cleaned_Data!$D$2:$D$499,4)),VALUE(MID(Cleaned_Data!$D$2:$D$499,4,2)),VALUE(LEFT(Cleaned_Data!$D$2:$D$499,2))),0)>=DATE(YEAR(G27),MONTH(G27),1))*(IFERROR(DATE(VALUE(RIGHT(Cleaned_Data!$D$2:$D$499,4)),VALUE(MID(Cleaned_Data!$D$2:$D$499,4,2)),VALUE(LEFT(Cleaned_Data!$D$2:$D$499,2))),0)<EDATE(G27,1))*Cleaned_Data!$P$2:$P$499) -> 0

Sheet Sales Dashboard
A1: SALES PERFORMANCE | EXECUTIVE DASHBOARD
A4: REGION | E4: CATEGORY | I4: ORDER MONTH
A5: All | E5: All | I5: All
A8: TOTAL SALES | E8: TOTAL ORDERS | I8: UNITS SOLD | M8: AVG ORDER VALUE
A9: =SUMIFS($D$16:$D$148,$A$16:$A$148,IF($A$5="All","*",$A$5),$B$16:$B$148,IF($E$5="All","*",$E$5),$C$16:$C$148,IF($I$5="All","*",$I$5)) -> 33924872 | E9: =SUMIFS($E$16:$E$148,$A$16:$A$148,IF($A$5="All","*",$A$5),$B$16:$B$148,IF($E$5="All","*",$E$5),$C$16:$C$148,IF($I$5="All","*",$I$5)) -> 496 | I9: =SUMIFS($F$16:$F$148,$A$16:$A$148,IF($A$5="All","*",$A$5),$B$16:$B$148,IF($E$5="All","*",$E$5),$C$16:$C$148,IF($I$5="All","*",$I$5)) -> 5207 | M9: =IFERROR(A9/E9,0) -> 68396.92
A13: SALES BREAKDOWN | All charts respond to the three filters above
A15: Region | B15: Category | C15: Month | D15: Sales | E15: Orders | F15: Quantity | H15: Month | I15: Sales | K15: Region | L15: Sales | N15: Category | O15: Sales
A16: East | B16: Electronics | C16: Jan | D16: 385020 | E16: 5 | F16: 41 | H16: Jan | I16: =SUMIFS($D$16:$D$148,$C$16:$C$148,H16,$A$16:$A$148,IF($A$5="All","*",$A$5),$B$16:$B$148,IF($E$5="All","*",$E$5)) -> 4579197.5 | K16: East | L16: =SUMIFS($D$16:$D$148,$A$16:$A$148,K16,$B$16:$B$148,IF($E$5="All","*",$E$5),$C$16:$C$148,IF($I$5="All","*",$I$5)) -> 4041922 | N16: Electronics | O16: =SUMIFS($D$16:$D$148,$B$16:$B$148,N16,$A$16:$A$148,IF($A$5="All","*",$A$5),$C$16:$C$148,IF($I$5="All","*",$I$5)) -> 26992394
A17: East | B17: Electronics | C17: Feb | D17: 4800 | E17: 1 | F17: 4 | H17: Feb | I17: =SUMIFS($D$16:$D$148,$C$16:$C$148,H17,$A$16:$A$148,IF($A$5="All","*",$A$5),$B$16:$B$148,IF($E$5="All","*",$E$5)) -> 4362197.2 | K17: North | L17: =SUMIFS($D$16:$D$148,$A$16:$A$148,K17,$B$16:$B$148,IF($E$5="All","*",$E$5),$C$16:$C$148,IF($I$5="All","*",$I$5)) -> 9197852.5 | N17: Home Appliances | O17: =SUMIFS($D$16:$D$148,$B$16:$B$148,N17,$A$16:$A$148,IF($A$5="All","*",$A$5),$C$16:$C$148,IF($I$5="All","*",$I$5)) -> 6816975
A18: East | B18: Electronics | C18: Mar | D18: 89950 | E18: 2 | F18: 17 | H18: Mar | I18: =SUMIFS($D$16:$D$148,$C$16:$C$148,H18,$A$16:$A$148,IF($A$5="All","*",$A$5),$B$16:$B$148,IF($E$5="All","*",$E$5)) -> 3651419.8 | K18: South | L18: =SUMIFS($D$16:$D$148,$A$16:$A$148,K18,$B$16:$B$148,IF($E$5="All","*",$E$5),$C$16:$C$148,IF($I$5="All","*",$I$5)) -> 7490491.5 | N18: Stationery | O18: =SUMIFS($D$16:$D$148,$B$16:$B$148,N18,$A$16:$A$148,IF($A$5="All","*",$A$5),$C$16:$C$148,IF($I$5="All","*",$I$5)) -> 115503.5
A19: East | B19: Electronics | C19: Apr | D19: 833100 | E19: 3 | F19: 35 | H19: Apr | I19: =SUMIFS($D$16:$D$148,$C$16:$C$148,H19,$A$16:$A$148,IF($A$5="All","*",$A$5),$B$16:$B$148,IF($E$5="All","*",$E$5)) -> 5689717.8 | K19: West | L19: =SUMIFS($D$16:$D$148,$A$16:$A$148,K19,$B$16:$B$148,IF($E$5="All","*",$E$5),$C$16:$C$148,IF($I$5="All","*",$I$5)) -> 13194606
A20: East | B20: Electronics | C20: May | D20: 172800 | E20: 1 | F20: 18 | H20: May | I20: =SUMIFS($D$16:$D$148,$C$16:$C$148,H20,$A$16:$A$148,IF($A$5="All","*",$A$5),$B$16:$B$148,IF($E$5="All","*",$E$5)) -> 3842092
A21: East | B21: Electronics | C21: Jun | D21: 15890 | E21: 2 | F21: 23 | H21: Jun | I21: =SUMIFS($D$16:$D$148,$C$16:$C$148,H21,$A$16:$A$148,IF($A$5="All","*",$A$5),$B$16:$B$148,IF($E$5="All","*",$E$5)) -> 1032385
A22: East | B22: Electronics | C22: Jul | D22: 3240 | E22: 1 | F22: 3 | H22: Jul | I22: =SUMIFS($D$16:$D$148,$C$16:$C$148,H22,$A$16:$A$148,IF($A$5="All","*",$A$5),$B$16:$B$148,IF($E$5="All","*",$E$5)) -> 1741047.5
A23: East | B23: Electronics | C23: Aug | D23: 627000 | E23: 1 | F23: 12 | H23: Aug | I23: =SUMIFS($D$16:$D$148,$C$16:$C$148,H23,$A$16:$A$148,IF($A$5="All","*",$A$5),$B$16:$B$148,IF($E$5="All","*",$E$5)) -> 1836526
A24: East | B24: Electronics | C24: Oct | D24: 9600 | E24: 1 | F24: 8 | H24: Sep | I24: =SUMIFS($D$16:$D$148,$C$16:$C$148,H24,$A$16:$A$148,IF($A$5="All","*",$A$5),$B$16:$B$148,IF($E$5="All","*",$E$5)) -> 1236111.5
A25: East | B25: Electronics | C25: Nov | D25: 568240 | E25: 2 | F25: 26 | H25: Oct | I25: =SUMIFS($D$16:$D$148,$C$16:$C$148,H25,$A$16:$A$148,IF($A$5="All","*",$A$5),$B$16:$B$148,IF($E$5="All","*",$E$5)) -> 1775603.5
A26: East | B26: Electronics | C26: Dec | D26: 24000 | E26: 2 | F26: 22 | H26: Nov | I26: =SUMIFS($D$16:$D$148,$C$16:$C$148,H26,$A$16:$A$148,IF($A$5="All","*",$A$5),$B$16:$B$148,IF($E$5="All","*",$E$5)) -> 1992715.2
A27: East | B27: Home Appliances | C27: Jan | D27: 82110 | E27: 3 | F27: 24 | H27: Dec | I27: =SUMIFS($D$16:$D$148,$C$16:$C$148,H27,$A$16:$A$148,IF($A$5="All","*",$A$5),$B$16:$B$148,IF($E$5="All","*",$E$5)) -> 2185859.5
A28: East | B28: Home Appliances | C28: Feb | D28: 74025 | E28: 2 | F28: 23
A29: East | B29: Home Appliances | C29: Mar | D29: 199175 | E29: 2 | F29: 35
A30: East | B30: Home Appliances | C30: Apr | D30: 283135 | E30: 5 | F30: 48
A31: East | B31: Home Appliances | C31: May | D31: 380375 | E31: 3 | F31: 49
A32: East | B32: Home Appliances | C32: Jun | D32: 8925 | E32: 1 | F32: 3
A33: East | B33: Home Appliances | C33: Jul | D33: 146060 | E33: 2 | F33: 22
A34: East | B34: Home Appliances | C34: Oct | D34: 88825 | E34: 1 | F34: 11
A35: East | B35: Home Appliances | C35: Dec | D35: 40375 | E35: 1 | F35: 5
A36: East | B36: Stationery | C36: Jan | D36: 681 | E36: 3 | F36: 22
A37: East | B37: Stationery | C37: Feb | D37: 114.75 | E37: 1 | F37: 3
A38: East | B38: Stationery | C38: Apr | D38: 1026 | E38: 1 | F38: 19
A39: East | B39: Stationery | C39: May | D39: 1514.75 | E39: 4 | F39: 64
... A148: West | B148: Stationery | C148: Dec | D148: 1488 | E148: 4 | F148: 41
